Workbook
Name Slicer_Category: #N/A
Name Slicer_Gender: #N/A
Name Slicer_Location: #N/A
Name Slicer_Season: #N/A
Name tblCombined: Table2[]

Sheet Customers
A1: Customer ID | B1: Customer name | C1: Age | D1: Location | E1: Gender
A2: C009 | B2: Linda Davis | C2: 53 | D2: Calabar | E2: Female
A3: C008 | B3: Rita Abubakar | C3: 27 | D3: Owerri | E3: Female
A4: C010 | B4: Grace Anderson | C4: 54 | D4: Abeokuta | E4: Female
A5: C139 | B5: Daniel White | C5: 20 | D5: Uyo | E5: Male
A6: C047 | B6: Tunde Jackson | C6: 52 | D6: Ilorin | E6: Male
A7: C060 | B7: Ifeoma Chukwu | C7: 58 | D7: Enugu | E7: Female
A8: C018 | B8: Tunde Uche | C8: 44 | D8: Lagos | E8: Male
A9: C091 | B9: James Balogun | C9: 41 | D9: Lagos | E9: Male
A10: C077 | B10: Laura Eze | C10: 20 | D10: Jos | E10: Female
A11: C114 | B11: Amara Johnson | C11: 58 | D11: Warri | E11: Female
A12: C051 | B12: John Okoro | C12: 30 | D12: Jos | E12: Male
A13: C118 | B13: Blessing Moore | C13: 18 | D13: Kano | E13: Female
... A144: C119 | B144: Peter Suleiman | C144: 38 | D144: Ibadan | E144: Male

Sheet Promo Codes
A1: Promo Code | B1: Discount
A2: WELCOME10 | B2: 0.1
A3: SEASON15 | B3: 0.15
A4: VIP20 | B4: 0.2
A5: FLASH5 | B5: 0.05

Sheet Products
A1: Product ID | B1: Category | C1: Product Name | D1: Price
A2: P01 | B2: Clothing | C2: Ankara Dress | D2: 68
A3: P02 | B3: Clothing | C3: Denim Jacket | D3: 95
A4: P03 | B4: Clothing | C4: Silk Blouse | D4: 54
A5: P04 | B5: Clothing | C5: Maxi Gown | D5: 120
A6: P05 | B6: Clothing | C6: Linen Trousers | D6: 47
A7: P06 | B7: Clothing | C7: Kaftan | D7: 89
A8: P07 | B8: Clothing | C8: Blazer | D8: 135
A9: P08 | B9: Clothing | C9: Jumpsuit | D9: 76
A10: P09 | B10: Clothing | C10: Wrap Skirt | D10: 42
A11: P10 | B11: Clothing | C11: Knit Sweater | D11: 58
A12: P11 | B12: Accessories | C12: Beaded Necklace | D12: 25
A13: P12 | B13: Accessories | C13: Leather Handbag | D13: 145
... A21: P20 | B21: Accessories | C21: Waist Belt | D21: 33

Sheet DashboardData
A1: Sum of Price | B1: Distinct Count of Customer ID | C1: Average of Price2 | H1: Sum of Price | I1: Column Labels
A2: 421 | B2: 4 | C2: 70.166667 | H2: Row Labels | I2: Accessories | J2: Clothing | K2: Grand Total
A3: ="$"&TEXT(A2,"#,##0") -> $421 | C3: ="$"&TEXT(C2,"0.00") -> $70.17 | H3: Fall | I3: 148 | K3: 148
A4: Row Labels | B4: Sum of Price | E4: Row Labels | F4: Sum of Price | H4: Spring | I4: 48 | K4: 48
A5: Male | B5: 421 | E5: Ilorin | F5: 421 | H5: Summer | J5: 177 | K5: 177
A6: Grand Total | B6: 421 | E6: Grand Total | F6: 421 | H6: Winter | I6: 48 | K6: 48
H7: Grand Total | I7: 244 | J7: 177 | K7: 421
A9: Row Labels | B9: Sum of Price
A10: 20-40 | B10: 48
A11: 40-60 | B11: 373 | I11: Count of Promo Code | J11: Percentage of promo code | L11: Row Labels | M11: Sum of Price
A12: Grand Total | B12: 421 | I12: 3 | J12: =GETPIVOTDATA("[Measures].[Count of Promo Code]",$I$11)/GETPIVOTDATA("[Measures].[Count of Order ID]",$B$16) -> 0.5 | L12: Accessories | M12: 244
L13: Clothing | M13: 177
L14: Grand Total | M14: 421
K15: =TEXT(J12,"0%") -> 50%
B16: Row Labels | C16: Count of Order ID
B17: Bank Transfer | C17: 4
B18: Debit Card | C18: 1 | J18: Row Labels | K18: Distinct Count of Customer ID
B19: PayPal | C19: 1 | J19: One-Time Customer | K19: 3
B20: Grand Total | C20: 6 | H20: Row Labels | I20: Count of Customer ID | J20: Repeat Customer | K20: 1
H21: No Code | I21: 3 | J21: Grand Total | K21: 4
H22: Used Code | I22: 3
H23: Grand Total | I23: 6

Sheet Dashboard

Sheet Combined Data
A1: Order ID | B1: Customer ID | C1: Product ID | D1: Order Date | E1: Payment Method | F1: Promo Code | G1: Customer Name | H1: Gender | I1: Age | J1: Location | K1: Category | L1: Product Name | M1: Price | N1: Season | O1: Age Group | P1: Repeat Customer | Q1: Promo Used
A2: 5012 | B2: C004 | C2: P10 | D2: 46266 | E2: Cash on Delivery | F2: WELCOME10 | G2: =INDEX(Customers!B:B,MATCH(B2,Customers!A:A,0)) -> Steven Johnson | H2: =INDEX(Customers!E:E,MATCH(B2,Customers!A:A,0)) -> Male | I2: =INDEX(Customers!C:C,MATCH(B2,Customers!A:A,0)) -> 33 | J2: =INDEX(Customers!D:D,MATCH(B2,Customers!A:A,0)) -> Abuja | K2: =INDEX(Products!B:B,MATCH(C2,Products!A:A,0)) -> Clothing | L2: =INDEX(Products!C:C,MATCH(C2,Products!A:A,0)) -> Knit Sweater | M2: =INDEX(Products!D:D,MATCH(C2,Products!A:A,0)) -> 58 | N2: =CHOOSE(MONTH(D2),"Winter","Winter","Spring","Spring","Spring","Summer","Summer","Summer","Fall","Fall","Fall","Winter") -> Fall | O2: =IF(I2<20,"<20",IF(I2<40,"20-40",IF(I2<60,"40-60","60+"))) -> 20-40 | P2: =IF(COUNTIF(B:B,B2)>1,"Yes","No") -> Yes | Q2: =IF(F2="","No Code","Used Code") -> Used Code
A3: 5033 | B3: C014 | C3: P15 | D3: 46085 | E3: Debit Card | G3: =INDEX(Customers!B:B,MATCH(B3,Customers!A:A,0)) -> Mark Davis | H3: =INDEX(Customers!E:E,MATCH(B3,Customers!A:A,0)) -> Male | I3: =INDEX(Customers!C:C,MATCH(B3,Customers!A:A,0)) -> 33 | J3: =INDEX(Customers!D:D,MATCH(B3,Customers!A:A,0)) -> Jos | K3: =INDEX(Products!B:B,MATCH(C3,Products!A:A,0)) -> Accessories | L3: =INDEX(Products!C:C,MATCH(C3,Products!A:A,0)) -> Tote Bag | M3: =INDEX(Products!D:D,MATCH(C3,Products!A:A,0)) -> 62 | N3: =CHOOSE(MONTH(D3),"Winter","Winter","Spring","Spring","Spring","Summer","Summer","Summer","Fall","Fall","Fall","Winter") -> Spring | O3: =IF(I3<20,"<20",IF(I3<40,"20-40",IF(I3<60,"40-60","60+"))) -> 20-40 | P3: =IF(COUNTIF(B:B,B3)>1,"Yes","No") -> Yes | Q3: =IF(F3="","No Code","Used Code") -> No Code
A4: 5117 | B4: C056 | C4: P20 | D4: 46045 | E4: PayPal | F4: VIP20 | G4: =INDEX(Customers!B:B,MATCH(B4,Customers!A:A,0)) -> Aisha Bello | H4: =INDEX(Customers!E:E,MATCH(B4,Customers!A:A,0)) -> Female | I4: =INDEX(Customers!C:C,MATCH(B4,Customers!A:A,0)) -> 32 | J4: =INDEX(Customers!D:D,MATCH(B4,Customers!A:A,0)) -> Kaduna | K4: =INDEX(Products!B:B,MATCH(C4,Products!A:A,0)) -> Accessories | L4: =INDEX(Products!C:C,MATCH(C4,Products!A:A,0)) -> Waist Belt | M4: =INDEX(Products!D:D,MATCH(C4,Products!A:A,0)) -> 33 | N4: =CHOOSE(MONTH(D4),"Winter","Winter","Spring","Spring","Spring","Summer","Summer","Summer","Fall","Fall","Fall","Winter") -> Winter | O4: =IF(I4<20,"<20",IF(I4<40,"20-40",IF(I4<60,"40-60","60+"))) -> 20-40 | P4: =IF(COUNTIF(B:B,B4)>1,"Yes","No") -> Yes | Q4: =IF(F4="","No Code","Used Code") -> Used Code
A5: 5201 | B5: C099 | C5: P19 | D5: 46041 | E5: Card | G5: =INDEX(Customers!B:B,MATCH(B5,Customers!A:A,0)) -> Ifeoma Martin | H5: =INDEX(Customers!E:E,MATCH(B5,Customers!A:A,0)) -> Female | I5: =INDEX(Customers!C:C,MATCH(B5,Customers!A:A,0)) -> 22 | J5: =INDEX(Customers!D:D,MATCH(B5,Customers!A:A,0)) -> Kano | K5: =INDEX(Products!B:B,MATCH(C5,Products!A:A,0)) -> Accessories | L5: =INDEX(Products!C:C,MATCH(C5,Products!A:A,0)) -> Earrings | M5: =INDEX(Products!D:D,MATCH(C5,Products!A:A,0)) -> 19 | N5: =CHOOSE(MONTH(D5),"Winter","Winter","Spring","Spring","Spring","Summer","Summer","Summer","Fall","Fall","Fall","Winter") -> Winter | O5: =IF(I5<20,"<20",IF(I5<40,"20-40",IF(I5<60,"40-60","60+"))) -> 20-40 | P5: =IF(COUNTIF(B:B,B5)>1,"Yes","No") -> Yes | Q5: =IF(F5="","No Code","Used Code") -> No Code
A6: 5270 | B6: C130 | C6: P03 | D6: 45990 | E6: Bank Transfer | F6: VIP20 | G6: =INDEX(Customers!B:B,MATCH(B6,Customers!A:A,0)) -> Linda Chukwu | H6: =INDEX(Customers!E:E,MATCH(B6,Customers!A:A,0)) -> Female | I6: =INDEX(Customers!C:C,MATCH(B6,Customers!A:A,0)) -> 59 | J6: =INDEX(Customers!D:D,MATCH(B6,Customers!A:A,0)) -> Ibadan | K6: =INDEX(Products!B:B,MATCH(C6,Products!A:A,0)) -> Clothing | L6: =INDEX(Products!C:C,MATCH(C6,Products!A:A,0)) -> Silk Blouse | M6: =INDEX(Products!D:D,MATCH(C6,Products!A:A,0)) -> 54 | N6: =CHOOSE(MONTH(D6),"Winter","Winter","Spring","Spring","Spring","Summer","Summer","Summer","Fall","Fall","Fall","Winter") -> Fall | O6: =IF(I6<20,"<20",IF(I6<40,"20-40",IF(I6<60,"40-60","60+"))) -> 40-60 | P6: =IF(COUNTIF(B:B,B6)>1,"Yes","No") -> Yes | Q6: =IF(F6="","No Code","Used Code") -> Used Code
A7: 5154 | B7: C076 | C7: P10 | D7: 46106 | E7: Cash on Delivery | F7: FLASH5 | G7: =INDEX(Customers!B:B,MATCH(B7,Customers!A:A,0)) -> Michael Martin | H7: =INDEX(Customers!E:E,MATCH(B7,Customers!A:A,0)) -> Male | I7: =INDEX(Customers!C:C,MATCH(B7,Customers!A:A,0)) -> 53 | J7: =INDEX(Customers!D:D,MATCH(B7,Customers!A:A,0)) -> Unknown | K7: =INDEX(Products!B:B,MATCH(C7,Products!A:A,0)) -> Clothing | L7: =INDEX(Products!C:C,MATCH(C7,Products!A:A,0)) -> Knit Sweater | M7: =INDEX(Products!D:D,MATCH(C7,Products!A:A,0)) -> 58 | N7: =CHOOSE(MONTH(D7),"Winter","Winter","Spring","Spring","Spring","Summer","Summer","Summer","Fall","Fall","Fall","Winter") -> Spring | O7: =IF(I7<20,"<20",IF(I7<40,"20-40",IF(I7<60,"40-60","60+"))) -> 40-60 | P7: =IF(COUNTIF(B:B,B7)>1,"Yes","No") -> Yes | Q7: =IF(F7="","No Code","Used Code") -> Used Code
A8: 5259 | B8: C126 | C8: P08 | D8: 46358 | E8: Card | G8: =INDEX(Customers!B:B,MATCH(B8,Customers!A:A,0)) -> Angela Wilson | H8: =INDEX(Customers!E:E,MATCH(B8,Customers!A:A,0)) -> Female | I8: =INDEX(Customers!C:C,MATCH(B8,Customers!A:A,0)) -> 38 | J8: =INDEX(Customers!D:D,MATCH(B8,Customers!A:A,0)) -> Warri | K8: =INDEX(Products!B:B,MATCH(C8,Products!A:A,0)) -> Clothing | L8: =INDEX(Products!C:C,MATCH(C8,Products!A:A,0)) -> Jumpsuit | M8: =INDEX(Products!D:D,MATCH(C8,Products!A:A,0)) -> 76 | N8: =CHOOSE(MONTH(D8),"Winter","Winter","Spring","Spring","Spring","Summer","Summer","Summer","Fall","Fall","Fall","Winter") -> Winter | O8: =IF(I8<20,"<20",IF(I8<40,"20-40",IF(I8<60,"40-60","60+"))) -> 20-40 | P8: =IF(COUNTIF(B:B,B8)>1,"Yes","No") -> No | Q8: =IF(F8="","No Code","Used Code") -> No Code
A9: 5198 | B9: C098 | C9: P06 | D9: 45842 | E9: PayPal | G9: =INDEX(Customers!B:B,MATCH(B9,Customers!A:A,0)) -> Peter Johnson | H9: =INDEX(Customers!E:E,MATCH(B9,Customers!A:A,0)) -> Male | I9: =INDEX(Customers!C:C,MATCH(B9,Customers!A:A,0)) -> 35 | J9: =INDEX(Customers!D:D,MATCH(B9,Customers!A:A,0)) -> Lagos | K9: =INDEX(Products!B:B,MATCH(C9,Products!A:A,0)) -> Clothing | L9: =INDEX(Products!C:C,MATCH(C9,Products!A:A,0)) -> Kaftan | M9: =INDEX(Products!D:D,MATCH(C9,Products!A:A,0)) -> 89 | N9: =CHOOSE(MONTH(D9),"Winter","Winter","Spring","Spring","Spring","Summer","Summer","Summer","Fall","Fall","Fall","Winter") -> Summer | O9: =IF(I9<20,"<20",IF(I9<40,"20-40",IF(I9<60,"40-60","60+"))) -> 20-40 | P9: =IF(COUNTIF(B:B,B9)>1,"Yes","No") -> Yes | Q9: =IF(F9="","No Code","Used Code") -> No Code
A10: 5039 | B10: C017 | C10: P03 | D10: 46115 | E10: PayPal | G10: =INDEX(Customers!B:B,MATCH(B10,Customers!A:A,0)) -> Grace Taylor | H10: =INDEX(Customers!E:E,MATCH(B10,Customers!A:A,0)) -> Female | I10: =INDEX(Customers!C:C,MATCH(B10,Customers!A:A,0)) -> 44 | J10: =INDEX(Customers!D:D,MATCH(B10,Customers!A:A,0)) -> Port Harcourt | K10: =INDEX(Products!B:B,MATCH(C10,Products!A:A,0)) -> Clothing | L10: =INDEX(Products!C:C,MATCH(C10,Products!A:A,0)) -> Silk Blouse | M10: =INDEX(Products!D:D,MATCH(C10,Products!A:A,0)) -> 54 | N10: =CHOOSE(MONTH(D10),"Winter","Winter","Spring","Spring","Spring","Summer","Summer","Summer","Fall","Fall","Fall","Winter") -> Spring | O10: =IF(I10<20,"<20",IF(I10<40,"20-40",IF(I10<60,"40-60","60+"))) -> 40-60 | P10: =IF(COUNTIF(B:B,B10)>1,"Yes","No") -> Yes | Q10: =IF(F10="","No Code","Used Code") -> No Code
A11: 5085 | B11: C040 | C11: P03 | D11: 45896 | E11: Cash on Delivery | F11: WELCOME10 | G11: =INDEX(Customers!B:B,MATCH(B11,Customers!A:A,0)) -> Nkechi Okoro | H11: =INDEX(Customers!E:E,MATCH(B11,Customers!A:A,0)) -> Female | I11: =INDEX(Customers!C:C,MATCH(B11,Customers!A:A,0)) -> 19 | J11: =INDEX(Customers!D:D,MATCH(B11,Customers!A:A,0)) -> Abuja | K11: =INDEX(Products!B:B,MATCH(C11,Products!A:A,0)) -> Clothing | L11: =INDEX(Products!C:C,MATCH(C11,Products!A:A,0)) -> Silk Blouse | M11: =INDEX(Products!D:D,MATCH(C11,Products!A:A,0)) -> 54 | N11: =CHOOSE(MONTH(D11),"Winter","Winter","Spring","Spring","Spring","Summer","Summer","Summer","Fall","Fall","Fall","Winter") -> Summer | O11: =IF(I11<20,"<20",IF(I11<40,"20-40",IF(I11<60,"40-60","60+"))) -> <20 | P11: =IF(COUNTIF(B:B,B11)>1,"Yes","No") -> Yes | Q11: =IF(F11="","No Code","Used Code") -> Used Code
A12: 5088 | B12: C042 | C12: P01 | D12: 45788 | E12: Card | F12: WELCOME10 | G12: =INDEX(Customers!B:B,MATCH(B12,Customers!A:A,0)) -> Mark Okoro | H12: =INDEX(Customers!E:E,MATCH(B12,Customers!A:A,0)) -> Male | I12: =INDEX(Customers!C:C,MATCH(B12,Customers!A:A,0)) -> 41 | J12: =INDEX(Customers!D:D,MATCH(B12,Customers!A:A,0)) -> Unknown | K12: =INDEX(Products!B:B,MATCH(C12,Products!A:A,0)) -> Clothing | L12: =INDEX(Products!C:C,MATCH(C12,Products!A:A,0)) -> Ankara Dress | M12: =INDEX(Products!D:D,MATCH(C12,Products!A:A,0)) -> 68 | N12: =CHOOSE(MONTH(D12),"Winter","Winter","Spring","Spring","Spring","Summer","Summer","Summer","Fall","Fall","Fall","Winter") -> Spring | O12: =IF(I12<20,"<20",IF(I12<40,"20-40",IF(I12<60,"40-60","60+"))) -> 40-60 | P12: =IF(COUNTIF(B:B,B12)>1,"Yes","No") -> No | Q12: =IF(F12="","No Code","Used Code") -> Used Code
A13: 5205 | B13: C101 | C13: P07 | D13: 46083 | E13: Cash on Delivery | G13: =INDEX(Customers!B:B,MATCH(B13,Customers!A:A,0)) -> Fatima Eze | H13: =INDEX(Customers!E:E,MATCH(B13,Customers!A:A,0)) -> Female | I13: =INDEX(Customers!C:C,MATCH(B13,Customers!A:A,0)) -> 25 | J13: =INDEX(Customers!D:D,MATCH(B13,Customers!A:A,0)) -> Kaduna | K13: =INDEX(Products!B:B,MATCH(C13,Products!A:A,0)) -> Clothing | L13: =INDEX(Products!C:C,MATCH(C13,Products!A:A,0)) -> Blazer | M13: =INDEX(Products!D:D,MATCH(C13,Products!A:A,0)) -> 135 | N13: =CHOOSE(MONTH(D13),"Winter","Winter","Spring","Spring","Spring","Summer","Summer","Summer","Fall","Fall","Fall","Winter") -> Spring | O13: =IF(I13<20,"<20",IF(I13<40,"20-40",IF(I13<60,"40-60","60+"))) -> 20-40 | P13: =IF(COUNTIF(B:B,B13)>1,"Yes","No") -> No | Q13: =IF(F13="","No Code","Used Code") -> No Code
A14: 5181 | B14: C091 | C14: P11 | D14: 46115 | E14: PayPal | G14: =INDEX(Customers!B:B,MATCH(B14,Customers!A:A,0)) -> James Balogun | H14: =INDEX(Customers!E:E,MATCH(B14,Customers!A:A,0)) -> Male | I14: =INDEX(Customers!C:C,MATCH(B14,Customers!A:A,0)) -> 41 | J14: =INDEX(Customers!D:D,MATCH(B14,Customers!A:A,0)) -> Lagos | K14: =INDEX(Products!B:B,MATCH(C14,Products!A:A,0)) -> Accessories | L14: =INDEX(Products!C:C,MATCH(C14,Products!A:A,0)) -> Beaded Necklace | M14: =INDEX(Products!D:D,MATCH(C14,Products!A:A,0)) -> 25 | N14: =CHOOSE(MONTH(D14),"Winter","Winter","Spring","Spring","Spring","Summer","Summer","Summer","Fall","Fall","Fall","Winter") -> Spring | O14: =IF(I14<20,"<20",IF(I14<40,"20-40",IF(I14<60,"40-60","60+"))) -> 40-60 | P14: =IF(COUNTIF(B:B,B14)>1,"Yes","No") -> No | Q14: =IF(F14="","No Code","Used Code") -> No Code
A15: 5292 | B15: C137 | C15: P06 | D15: 46035 | E15: Bank Transfer | G15: =INDEX(Customers!B:B,MATCH(B15,Customers!A:A,0)) -> John Balogun | H15: =INDEX(Customers!E:E,MATCH(B15,Customers!A:A,0)) -> Male | I15: =INDEX(Customers!C:C,MATCH(B15,Customers!A:A,0)) -> 31 | J15: =INDEX(Customers!D:D,MATCH(B15,Customers!A:A,0)) -> Ibadan | K15: =INDEX(Products!B:B,MATCH(C15,Products!A:A,0)) -> Clothing | L15: =INDEX(Products!C:C,MATCH(C15,Products!A:A,0)) -> Kaftan | M15: =INDEX(Products!D:D,MATCH(C15,Products!A:A,0)) -> 89 | N15: =CHOOSE(MONTH(D15),"Winter","Winter","Spring","Spring","Spring","Summer","Summer","Summer","Fall","Fall","Fall","Winter") -> Winter | O15: =IF(I15<20,"<20",IF(I15<40,"20-40",IF(I15<60,"40-60","60+"))) -> 20-40 | P15: =IF(COUNTIF(B:B,B15)>1,"Yes","No") -> No | Q15: =IF(F15="","No Code","Used Code") -> No Code
A16: 5296 | B16: C139 | C16: P17 | D16: 46162 | E16: Card | F16: WELCOME10 | G16: =INDEX(Customers!B:B,MATCH(B16,Customers!A:A,0)) -> Daniel White | H16: =INDEX(Customers!E:E,MATCH(B16,Customers!A:A,0)) -> Male | I16: =INDEX(Customers!C:C,MATCH(B16,Customers!A:A,0)) -> 20 | J16: =INDEX(Customers!D:D,MATCH(B16,Customers!A:A,0)) -> Uyo | K16: =INDEX(Products!B:B,MATCH(C16,Products!A:A,0)) -> Accessories | L16: =INDEX(Products!C:C,MATCH(C16,Products!A:A,0)) -> Ankle Boots | M16: =INDEX(Products!D:D,MATCH(C16,Products!A:A,0)) -> 110 | N16: =CHOOSE(MONTH(D16),"Winter","Winter","Spring","Spring","Spring","Summer","Summer","Summer","Fall","Fall","Fall","Winter") -> Spring | O16: =IF(I16<20,"<20",IF(I16<40,"20-40",IF(I16<60,"40-60","60+"))) -> 20-40 | P16: =IF(COUNTIF(B:B,B16)>1,"Yes","No") -> Yes | Q16: =IF(F16="","No Code","Used Code") -> Used Code
A17: 5243 | B17: C121 | C17: P17 | D17: 46128 | E17: Cash on Delivery | F17: VIP20 | G17: =INDEX(Customers!B:B,MATCH(B17,Customers!A:A,0)) -> Chioma Wilson | H17: =INDEX(Customers!E:E,MATCH(B17,Customers!A:A,0)) -> Female | I17: =INDEX(Customers!C:C,MATCH(B17,Customers!A:A,0)) -> 23 | J17: =INDEX(Customers!D:D,MATCH(B17,Customers!A:A,0)) -> Kaduna | K17: =INDEX(Products!B:B,MATCH(C17,Products!A:A,0)) -> Accessories | L17: =INDEX(Products!C:C,MATCH(C17,Products!A:A,0)) -> Ankle Boots | M17: =INDEX(Products!D:D,MATCH(C17,Products!A:A,0)) -> 110 | N17: =CHOOSE(MONTH(D17),"Winter","Winter","Spring","Spring","Spring","Summer","Summer","Summer","Fall","Fall","Fall","Winter") -> Spring | O17: =IF(I17<20,"<20",IF(I17<40,"20-40",IF(I17<60,"40-60","60+"))) -> 20-40 | P17: =IF(COUNTIF(B:B,B17)>1,"Yes","No") -> Yes | Q17: =IF(F17="","No Code","Used Code") -> Used Code
A18: 5175 | B18: C087 | C18: P14 | D18: 45982 | E18: PayPal | G18: =INDEX(Customers!B:B,MATCH(B18,Customers!A:A,0)) -> Tunde Eze | H18: =INDEX(Customers!E:E,MATCH(B18,Customers!A:A,0)) -> Male | I18: =INDEX(Customers!C:C,MATCH(B18,Customers!A:A,0)) -> 26 | J18: =INDEX(Customers!D:D,MATCH(B18,Customers!A:A,0)) -> Kaduna | K18: =INDEX(Products!B:B,MATCH(C18,Products!A:A,0)) -> Accessories | L18: =INDEX(Products!C:C,MATCH(C18,Products!A:A,0)) -> Hair Scarf | M18: =INDEX(Products!D:D,MATCH(C18,Products!A:A,0)) -> 15 | N18: =CHOOSE(MONTH(D18),"Winter","Winter","Spring","Spring","Spring","Summer","Summer","Summer","Fall","Fall","Fall","Winter") -> Fall | O18: =IF(I18<20,"<20",IF(I18<40,"20-40",IF(I18<60,"40-60","60+"))) -> 20-40 | P18: =IF(COUNTIF(B:B,B18)>1,"Yes","No") -> Yes | Q18: =IF(F18="","No Code","Used Code") -> No Code
A19: 5146 | B19: C071 | C19: P12 | D19: 46048 | E19: Cash on Delivery | F19: VIP20 | G19: =INDEX(Customers!B:B,MATCH(B19,Customers!A:A,0)) -> Musa Harris | H19: =INDEX(Customers!E:E,MATCH(B19,Customers!A:A,0)) -> Male | I19: =INDEX(Customers!C:C,MATCH(B19,Customers!A:A,0)) -> 51 | J19: =INDEX(Customers!D:D,MATCH(B19,Customers!A:A,0)) -> Benin City | K19: =INDEX(Products!B:B,MATCH(C19,Products!A:A,0)) -> Accessories | L19: =INDEX(Products!C:C,MATCH(C19,Products!A:A,0)) -> Leather Handbag | M19: =INDEX(Products!D:D,MATCH(C19,Products!A:A,0)) -> 145 | N19: =CHOOSE(MONTH(D19),"Winter","Winter","Spring","Spring","Spring","Summer","Summer","Summer","Fall","Fall","Fall","Winter") -> Winter | O19: =IF(I19<20,"<20",IF(I19<40,"20-40",IF(I19<60,"40-60","60+"))) -> 40-60 | P19: =IF(COUNTIF(B:B,B19)>1,"Yes","No") -> No | Q19: =IF(F19="","No Code","Used Code") -> Used Code
A20: 5268 | B20: C130 | C20: P07 | D20: 45983 | E20: Bank Transfer | F20: VIP20 | G20: =INDEX(Customers!B:B,MATCH(B20,Customers!A:A,0)) -> Linda Chukwu | H20: =INDEX(Customers!E:E,MATCH(B20,Customers!A:A,0)) -> Female | I20: =INDEX(Customers!C:C,MATCH(B20,Customers!A:A,0)) -> 59 | J20: =INDEX(Customers!D:D,MATCH(B20,Customers!A:A,0)) -> Ibadan | K20: =INDEX(Products!B:B,MATCH(C20,Products!A:A,0)) -> Clothing | L20: =INDEX(Products!C:C,MATCH(C20,Products!A:A,0)) -> Blazer | M20: =INDEX(Products!D:D,MATCH(C20,Products!A:A,0)) -> 135 | N20: =CHOOSE(MONTH(D20),"Winter","Winter","Spring","Spring","Spring","Summer","Summer","Summer","Fall","Fall","Fall","Winter") -> Fall | O20: =IF(I20<20,"<20",IF(I20<40,"20-40",IF(I20<60,"40-60","60+"))) -> 40-60 | P20: =IF(COUNTIF(B:B,B20)>1,"Yes","No") -> Yes | Q20: =IF(F20="","No Code","Used Code") -> Used Code
A21: 5206 | B21: C102 | C21: P18 | D21: 46148 | E21: Card | F21: WELCOME10 | G21: =INDEX(Customers!B:B,MATCH(B21,Customers!A:A,0)) -> Chioma Suleiman | H21: =INDEX(Customers!E:E,MATCH(B21,Customers!A:A,0)) -> Female | I21: =INDEX(Customers!C:C,MATCH(B21,Customers!A:A,0)) -> 44 | J21: =INDEX(Customers!D:D,MATCH(B21,Customers!A:A,0)) -> Ilorin | K21: =INDEX(Products!B:B,MATCH(C21,Products!A:A,0)) -> Accessories | L21: =INDEX(Products!C:C,MATCH(C21,Products!A:A,0)) -> Clutch Purse | M21: =INDEX(Products!D:D,MATCH(C21,Products!A:A,0)) -> 48 | N21: =CHOOSE(MONTH(D21),"Winter","Winter","Spring","Spring","Spring","Summer","Summer","Summer","Fall","Fall","Fall","Winter") -> Spring | O21: =IF(I21<20,"<20",IF(I21<40,"20-40",IF(I21<60,"40-60","60+"))) -> 40-60 | P21: =IF(COUNTIF(B:B,B21)>1,"Yes","No") -> No | Q21: =IF(F21="","No Code","Used Code") -> Used Code
A22: 5054 | B22: C023 | C22: P09 | D22: 45898 | E22: Bank Transfer | G22: =INDEX(Customers!B:B,MATCH(B22,Customers!A:A,0)) -> Daniel Jackson | H22: =INDEX(Customers!E:E,MATCH(B22,Customers!A:A,0)) -> Male | I22: =INDEX(Customers!C:C,MATCH(B22,Customers!A:A,0)) -> 42 | J22: =INDEX(Customers!D:D,MATCH(B22,Customers!A:A,0)) -> Ilorin | K22: =INDEX(Products!B:B,MATCH(C22,Products!A:A,0)) -> Clothing | L22: =INDEX(Products!C:C,MATCH(C22,Products!A:A,0)) -> Wrap Skirt | M22: =INDEX(Products!D:D,MATCH(C22,Products!A:A,0)) -> 42 | N22: =CHOOSE(MONTH(D22),"Winter","Winter","Spring","Spring","Spring","Summer","Summer","Summer","Fall","Fall","Fall","Winter") -> Summer | O22: =IF(I22<20,"<20",IF(I22<40,"20-40",IF(I22<60,"40-60","60+"))) -> 40-60 | P22: =IF(COUNTIF(B:B,B22)>1,"Yes","No") -> Yes | Q22: =IF(F22="","No Code","Used Code") -> No Code
A23: 5171 | B23: C085 | C23: P19 | D23: 45889 | E23: PayPal | G23: =INDEX(Customers!B:B,MATCH(B23,Customers!A:A,0)) -> James Brown | H23: =INDEX(Customers!E:E,MATCH(B23,Customers!A:A,0)) -> Male | I23: =INDEX(Customers!C:C,MATCH(B23,Customers!A:A,0)) -> 60 | J23: =INDEX(Customers!D:D,MATCH(B23,Customers!A:A,0)) -> Kano | K23: =INDEX(Products!B:B,MATCH(C23,Products!A:A,0)) -> Accessories | L23: =INDEX(Products!C:C,MATCH(C23,Products!A:A,0)) -> Earrings | M23: =INDEX(Products!D:D,MATCH(C23,Products!A:A,0)) -> 19 | N23: =CHOOSE(MONTH(D23),"Winter","Winter","Spring","Spring","Spring","Summer","Summer","Summer","Fall","Fall","Fall","Winter") -> Summer | O23: =IF(I23<20,"<20",IF(I23<40,"20-40",IF(I23<60,"40-60","60+"))) -> 60+ | P23: =IF(COUNTIF(B:B,B23)>1,"Yes","No") -> No | Q23: =IF(F23="","No Code","Used Code") -> No Code
A24: 5250 | B24: C122 | C24: P12 | D24: 46164 | E24: Bank Transfer | F24: FLASH5 | G24: =INDEX(Customers!B:B,MATCH(B24,Customers!A:A,0)) -> Yusuf Thomas | H24: =INDEX(Customers!E:E,MATCH(B24,Customers!A:A,0)) -> Male | I24: =INDEX(Customers!C:C,MATCH(B24,Customers!A:A,0)) -> 30 | J24: =INDEX(Customers!D:D,MATCH(B24,Customers!A:A,0)) -> Ibadan | K24: =INDEX(Products!B:B,MATCH(C24,Products!A:A,0)) -> Accessories | L24: =INDEX(Products!C:C,MATCH(C24,Products!A:A,0)) -> Leather Handbag | M24: =INDEX(Products!D:D,MATCH(C24,Products!A:A,0)) -> 145 | N24: =CHOOSE(MONTH(D24),"Winter","Winter","Spring","Spring","Spring","Summer","Summer","Summer","Fall","Fall","Fall","Winter") -> Spring | O24: =IF(I24<20,"<20",IF(I24<40,"20-40",IF(I24<60,"40-60","60+"))) -> 20-40 | P24: =IF(COUNTIF(B:B,B24)>1,"Yes","No") -> Yes | Q24: =IF(F24="","No Code","Used Code") -> Used Code
A25: 5246 | B25: C121 | C25: P02 | D25: 45975 | E25: PayPal | F25: VIP20 | G25: =INDEX(Customers!B:B,MATCH(B25,Customers!A:A,0)) -> Chioma Wilson | H25: =INDEX(Customers!E:E,MATCH(B25,Customers!A:A,0)) -> Female | I25: =INDEX(Customers!C:C,MATCH(B25,Customers!A:A,0)) -> 23 | J25: =INDEX(Customers!D:D,MATCH(B25,Customers!A:A,0)) -> Kaduna | K25: =INDEX(Products!B:B,MATCH(C25,Products!A:A,0)) -> Clothing | L25: =INDEX(Products!C:C,MATCH(C25,Products!A:A,0)) -> Denim Jacket | M25: =INDEX(Products!D:D,MATCH(C25,Products!A:A,0)) -> 95 | N25: =CHOOSE(MONTH(D25),"Winter","Winter","Spring","Spring","Spring","Summer","Summer","Summer","Fall","Fall","Fall","Winter") -> Fall | O25: =IF(I25<20,"<20",IF(I25<40,"20-40",IF(I25<60,"40-60","60+"))) -> 20-40 | P25: =IF(COUNTIF(B:B,B25)>1,"Yes","No") -> Yes | Q25: =IF(F25="","No Code","Used Code") -> Used Code
A26: 5249 | B26: C122 | C26: P07 | D26: 46073 | E26: Card | F26: SEASON15 | G26: =INDEX(Customers!B:B,MATCH(B26,Customers!A:A,0)) -> Yusuf Thomas | H26: =INDEX(Customers!E:E,MATCH(B26,Customers!A:A,0)) -> Male | I26: =INDEX(Customers!C:C,MATCH(B26,Customers!A:A,0)) -> 30 | J26: =INDEX(Customers!D:D,MATCH(B26,Customers!A:A,0)) -> Ibadan | K26: =INDEX(Products!B:B,MATCH(C26,Products!A:A,0)) -> Clothing | L26: =INDEX(Products!C:C,MATCH(C26,Products!A:A,0)) -> Blazer | M26: =INDEX(Products!D:D,MATCH(C26,Products!A:A,0)) -> 135 | N26: =CHOOSE(MONTH(D26),"Winter","Winter","Spring","Spring","Spring","Summer","Summer","Summer","Fall","Fall","Fall","Winter") -> Winter | O26: =IF(I26<20,"<20",IF(I26<40,"20-40",IF(I26<60,"40-60","60+"))) -> 20-40 | P26: =IF(COUNTIF(B:B,B26)>1,"Yes","No") -> Yes | Q26: =IF(F26="","No Code","Used Code") -> Used Code
A27: 5014 | B27: C006 | C27: P05 | D27: 46109 | E27: Card | F27: FLASH5 | G27: =INDEX(Customers!B:B,MATCH(B27,Customers!A:A,0)) -> Linda Smith | H27: =INDEX(Customers!E:E,MATCH(B27,Customers!A:A,0)) -> Female | I27: =INDEX(Customers!C:C,MATCH(B27,Customers!A:A,0)) -> 54 | J27: =INDEX(Customers!D:D,MATCH(B27,Customers!A:A,0)) -> Uyo | K27: =INDEX(Products!B:B,MATCH(C27,Products!A:A,0)) -> Clothing | L27: =INDEX(Products!C:C,MATCH(C27,Products!A:A,0)) -> Linen Trousers | M27: =INDEX(Products!D:D,MATCH(C27,Products!A:A,0)) -> 47 | N27: =CHOOSE(MONTH(D27),"Winter","Winter","Spring","Spring","Spring","Summer","Summer","Summer","Fall","Fall","Fall","Winter") -> Spring | O27: =IF(I27<20,"<20",IF(I27<40,"20-40",IF(I27<60,"40-60","60+"))) -> 40-60 | P27: =IF(COUNTIF(B:B,B27)>1,"Yes","No") -> Yes | Q27: =IF(F27="","No Code","Used Code") -> Used Code
A28: 5179 | B28: C089 | C28: P03 | D28: 45948 | E28: Bank Transfer | F28: WELCOME10 | G28: =INDEX(Customers!B:B,MATCH(B28,Customers!A:A,0)) -> Sarah Jackson | H28: =INDEX(Customers!E:E,MATCH(B28,Customers!A:A,0)) -> Female | I28: =INDEX(Customers!C:C,MATCH(B28,Customers!A:A,0)) -> 45 | J28: =INDEX(Customers!D:D,MATCH(B28,Customers!A:A,0)) -> Unknown | K28: =INDEX(Products!B:B,MATCH(C28,Products!A:A,0)) -> Clothing | L28: =INDEX(Products!C:C,MATCH(C28,Products!A:A,0)) -> Silk Blouse | M28: =INDEX(Products!D:D,MATCH(C28,Products!A:A,0)) -> 54 | N28: =CHOOSE(MONTH(D28),"Winter","Winter","Spring","Spring","Spring","Summer","Summer","Summer","Fall","Fall","Fall","Winter") -> Fall | O28: =IF(I28<20,"<20",IF(I28<40,"20-40",IF(I28<60,"40-60","60+"))) -> 40-60 | P28: =IF(COUNTIF(B:B,B28)>1,"Yes","No") -> Yes | Q28: =IF(F28="","No Code","Used Code") -> Used Code
A29: 5102 | B29: C050 | C29: P19 | D29: 45997 | E29: Bank Transfer | G29: =INDEX(Customers!B:B,MATCH(B29,Customers!A:A,0)) -> Nkechi White | H29: =INDEX(Customers!E:E,MATCH(B29,Customers!A:A,0)) -> Female | I29: =INDEX(Customers!C:C,MATCH(B29,Customers!A:A,0)) -> 32 | J29: =INDEX(Customers!D:D,MATCH(B29,Customers!A:A,0)) -> Owerri | K29: =INDEX(Products!B:B,MATCH(C29,Products!A:A,0)) -> Accessories | L29: =INDEX(Products!C:C,MATCH(C29,Products!A:A,0)) -> Earrings | M29: =INDEX(Products!D:D,MATCH(C29,Products!A:A,0)) -> 19 | N29: =CHOOSE(MONTH(D29),"Winter","Winter","Spring","Spring","Spring","Summer","Summer","Summer","Fall","Fall","Fall","Winter") -> Winter | O29: =IF(I29<20,"<20",IF(I29<40,"20-40",IF(I29<60,"40-60","60+"))) -> 20-40 | P29: =IF(COUNTIF(B:B,B29)>1,"Yes","No") -> Yes | Q29: =IF(F29="","No Code","Used Code") -> No Code
A30: 5090 | B30: C043 | C30: P04 | D30: 45847 | E30: Bank Transfer | G30: =INDEX(Customers!B:B,MATCH(B30,Customers!A:A,0)) -> Grace Aliyu | H30: =INDEX(Customers!E:E,MATCH(B30,Customers!A:A,0)) -> Female | I30: =INDEX(Customers!C:C,MATCH(B30,Customers!A:A,0)) -> 49 | J30: =INDEX(Customers!D:D,MATCH(B30,Customers!A:A,0)) -> Kaduna | K30: =INDEX(Products!B:B,MATCH(C30,Products!A:A,0)) -> Clothing | L30: =INDEX(Products!C:C,MATCH(C30,Products!A:A,0)) -> Maxi Gown | M30: =INDEX(Products!D:D,MATCH(C30,Products!A:A,0)) -> 120 | N30: =CHOOSE(MONTH(D30),"Winter","Winter","Spring","Spring","Spring","Summer","Summer","Summer","Fall","Fall","Fall","Winter") -> Summer | O30: =IF(I30<20,"<20",IF(I30<40,"20-40",IF(I30<60,"40-60","60+"))) -> 40-60 | P30: =IF(COUNTIF(B:B,B30)>1,"Yes","No") -> Yes | Q30: =IF(F30="","No Code","Used Code") -> No Code
A31: 5136 | B31: C065 | C31: P05 | D31: 46066 | E31: Debit Card | F31: FLASH5 | G31: =INDEX(Customers!B:B,MATCH(B31,Customers!A:A,0)) -> Tunde Suleiman | H31: =INDEX(Customers!E:E,MATCH(B31,Customers!A:A,0)) -> Male | I31: =INDEX(Customers!C:C,MATCH(B31,Customers!A:A,0)) -> 53 | J31: =INDEX(Customers!D:D,MATCH(B31,Customers!A:A,0)) -> Port Harcourt | K31: =INDEX(Products!B:B,MATCH(C31,Products!A:A,0)) -> Clothing | L31: =INDEX(Products!C:C,MATCH(C31,Products!A:A,0)) -> Linen Trousers | M31: =INDEX(Products!D:D,MATCH(C31,Products!A:A,0)) -> 47 | N31: =CHOOSE(MONTH(D31),"Winter","Winter","Spring","Spring","Spring","Summer","Summer","Summer","Fall","Fall","Fall","Winter") -> Winter | O31: =IF(I31<20,"<20",IF(I31<40,"20-40",IF(I31<60,"40-60","60+"))) -> 40-60 | P31: =IF(COUNTIF(B:B,B31)>1,"Yes","No") -> Yes | Q31: =IF(F31="","No Code","Used Code") -> Used Code
A32: 5127 | B32: C059 | C32: P07 | D32: 45881 | E32: Card | G32: =INDEX(Customers!B:B,MATCH(B32,Customers!A:A,0)) -> Grace Wilson | H32: =INDEX(Customers!E:E,MATCH(B32,Customers!A:A,0)) -> Female | I32: =INDEX(Customers!C:C,MATCH(B32,Customers!A:A,0)) -> 30 | J32: =INDEX(Customers!D:D,MATCH(B32,Customers!A:A,0)) -> Kaduna | K32: =INDEX(Products!B:B,MATCH(C32,Products!A:A,0)) -> Clothing | L32: =INDEX(Products!C:C,MATCH(C32,Products!A:A,0)) -> Blazer | M32: =INDEX(Products!D:D,MATCH(C32,Products!A:A,0)) -> 135 | N32: =CHOOSE(MONTH(D32),"Winter","Winter","Spring","Spring","Spring","Summer","Summer","Summer","Fall","Fall","Fall","Winter") -> Summer | O32: =IF(I32<20,"<20",IF(I32<40,"20-40",IF(I32<60,"40-60","60+"))) -> 20-40 | P32: =IF(COUNTIF(B:B,B32)>1,"Yes","No") -> Yes | Q32: =IF(F32="","No Code","Used Code") -> No Code
A33: 5185 | B33: C093 | C33: P13 | D33: 45990 | E33: Debit Card | G33: =INDEX(Customers!B:B,MATCH(B33,Customers!A:A,0)) -> Halima Miller | H33: =INDEX(Customers!E:E,MATCH(B33,Customers!A:A,0)) -> Female | I33: =INDEX(Customers!C:C,MATCH(B33,Customers!A:A,0)) -> 51 | J33: =INDEX(Customers!D:D,MATCH(B33,Customers!A:A,0)) -> Uyo | K33: =INDEX(Products!B:B,MATCH(C33,Products!A:A,0)) -> Accessories | L33: =INDEX(Products!C:C,MATCH(C33,Products!A:A,0)) -> Sunglasses | M33: =INDEX(Products!D:D,MATCH(C33,Products!A:A,0)) -> 38 | N33: =CHOOSE(MONTH(D33),"Winter","Winter","Spring","Spring","Spring","Summer","Summer","Summer","Fall","Fall","Fall","Winter") -> Fall | O33: =IF(I33<20,"<20",IF(I33<40,"20-40",IF(I33<60,"40-60","60+"))) -> 40-60 | P33: =IF(COUNTIF(B:B,B33)>1,"Yes","No") -> No | Q33: =IF(F33="","No Code","Used Code") -> No Code
A34: 5103 | B34: C051 | C34: P03 | D34: 46086 | E34: Cash on Delivery | F34: SEASON15 | G34: =INDEX(Customers!B:B,MATCH(B34,Customers!A:A,0)) -> John Okoro | H34: =INDEX(Customers!E:E,MATCH(B34,Customers!A:A,0)) -> Male | I34: =INDEX(Customers!C:C,MATCH(B34,Customers!A:A,0)) -> 30 | J34: =INDEX(Customers!D:D,MATCH(B34,Customers!A:A,0)) -> Jos | K34: =INDEX(Products!B:B,MATCH(C34,Products!A:A,0)) -> Clothing | L34: =INDEX(Products!C:C,MATCH(C34,Products!A:A,0)) -> Silk Blouse | M34: =INDEX(Products!D:D,MATCH(C34,Products!A:A,0)) -> 54 | N34: =CHOOSE(MONTH(D34),"Winter","Winter","Spring","Spring","Spring","Summer","Summer","Summer","Fall","Fall","Fall","Winter") -> Spring | O34: =IF(I34<20,"<20",IF(I34<40,"20-40",IF(I34<60,"40-60","60+"))) -> 20-40 | P34: =IF(COUNTIF(B:B,B34)>1,"Yes","No") -> Yes | Q34: =IF(F34="","No Code","Used Code") -> Used Code
A35: 5133 | B35: C062 | C35: P12 | D35: 46080 | E35: Bank Transfer | F35: WELCOME10 | G35: =INDEX(Customers!B:B,MATCH(B35,Customers!A:A,0)) -> Sarah Williams | H35: =INDEX(Customers!E:E,MATCH(B35,Customers!A:A,0)) -> Female | I35: =INDEX(Customers!C:C,MATCH(B35,Customers!A:A,0)) -> 26 | J35: =INDEX(Customers!D:D,MATCH(B35,Customers!A:A,0)) -> Lagos | K35: =INDEX(Products!B:B,MATCH(C35,Products!A:A,0)) -> Accessories | L35: =INDEX(Products!C:C,MATCH(C35,Products!A:A,0)) -> Leather Handbag | M35: =INDEX(Products!D:D,MATCH(C35,Products!A:A,0)) -> 145 | N35: =CHOOSE(MONTH(D35),"Winter","Winter","Spring","Spring","Spring","Summer","Summer","Summer","Fall","Fall","Fall","Winter") -> Winter | O35: =IF(I35<20,"<20",IF(I35<40,"20-40",IF(I35<60,"40-60","60+"))) -> 20-40 | P35: =IF(COUNTIF(B:B,B35)>1,"Yes","No") -> Yes | Q35: =IF(F35="","No Code","Used Code") -> Used Code
A36: 5078 | B36: C036 | C36: P09 | D36: 46127 | E36: Debit Card | G36: =INDEX(Customers!B:B,MATCH(B36,Customers!A:A,0)) -> Kevin Wilson | H36: =INDEX(Customers!E:E,MATCH(B36,Customers!A:A,0)) -> Male | I36: =INDEX(Customers!C:C,MATCH(B36,Customers!A:A,0)) -> 24 | J36: =INDEX(Customers!D:D,MATCH(B36,Customers!A:A,0)) -> Kaduna | K36: =INDEX(Products!B:B,MATCH(C36,Products!A:A,0)) -> Clothing | L36: =INDEX(Products!C:C,MATCH(C36,Products!A:A,0)) -> Wrap Skirt | M36: =INDEX(Products!D:D,MATCH(C36,Products!A:A,0)) -> 42 | N36: =CHOOSE(MONTH(D36),"Winter","Winter","Spring","Spring","Spring","Summer","Summer","Summer","Fall","Fall","Fall","Winter") -> Spring | O36: =IF(I36<20,"<20",IF(I36<40,"20-40",IF(I36<60,"40-60","60+"))) -> 20-40 | P36: =IF(COUNTIF(B:B,B36)>1,"Yes","No") -> Yes | Q36: =IF(F36="","No Code","Used Code") -> No Code
A37: 5289 | B37: C136 | C37: P01 | D37: 45849 | E37: Card | F37: SEASON15 | G37: =INDEX(Customers!B:B,MATCH(B37,Customers!A:A,0)) -> Adaeze Eze | H37: =INDEX(Customers!E:E,MATCH(B37,Customers!A:A,0)) -> Female | I37: =INDEX(Customers!C:C,MATCH(B37,Customers!A:A,0)) -> 22 | J37: =INDEX(Customers!D:D,MATCH(B37,Customers!A:A,0)) -> Calabar | K37: =INDEX(Products!B:B,MATCH(C37,Products!A:A,0)) -> Clothing | L37: =INDEX(Products!C:C,MATCH(C37,Products!A:A,0)) -> Ankara Dress | M37: =INDEX(Products!D:D,MATCH(C37,Products!A:A,0)) -> 68 | N37: =CHOOSE(MONTH(D37),"Winter","Winter","Spring","Spring","Spring","Summer","Summer","Summer","Fall","Fall","Fall","Winter") -> Summer | O37: =IF(I37<20,"<20",IF(I37<40,"20-40",IF(I37<60,"40-60","60+"))) -> 20-40 | P37: =IF(COUNTIF(B:B,B37)>1,"Yes","No") -> Yes | Q37: =IF(F37="","No Code","Used Code") -> Used Code
A38: 5261 | B38: C127 | C38: P20 | D38: 45918 | E38: Bank Transfer | F38: WELCOME10 | G38: =INDEX(Customers!B:B,MATCH(B38,Customers!A:A,0)) -> Tunde Davis | H38: =INDEX(Customers!E:E,MATCH(B38,Customers!A:A,0)) -> Male | I38: =INDEX(Customers!C:C,MATCH(B38,Customers!A:A,0)) -> 57 | J38: =INDEX(Customers!D:D,MATCH(B38,Customers!A:A,0)) -> Abeokuta | K38: =INDEX(Products!B:B,MATCH(C38,Products!A:A,0)) -> Accessories | L38: =INDEX(Products!C:C,MATCH(C38,Products!A:A,0)) -> Waist Belt | M38: =INDEX(Products!D:D,MATCH(C38,Products!A:A,0)) -> 33 | N38: =CHOOSE(MONTH(D38),"Winter","Winter","Spring","Spring","Spring","Summer","Summer","Summer","Fall","Fall","Fall","Winter") -> Fall | O38: =IF(I38<20,"<20",IF(I38<40,"20-40",IF(I38<60,"40-60","60+"))) -> 40-60 | P38: =IF(COUNTIF(B:B,B38)>1,"Yes","No") -> Yes | Q38: =IF(F38="","No Code","Used Code") -> Used Code
A39: 5079 | B39: C036 | C39: P10 | D39: 45989 | E39: PayPal | G39: =INDEX(Customers!B:B,MATCH(B39,Customers!A:A,0)) -> Kevin Wilson | H39: =INDEX(Customers!E:E,MATCH(B39,Customers!A:A,0)) -> Male | I39: =INDEX(Customers!C:C,MATCH(B39,Customers!A:A,0)) -> 24 | J39: =INDEX(Customers!D:D,MATCH(B39,Customers!A:A,0)) -> Kaduna | K39: =INDEX(Products!B:B,MATCH(C39,Products!A:A,0)) -> Clothing | L39: =INDEX(Products!C:C,MATCH(C39,Products!A:A,0)) -> Knit Sweater | M39: =INDEX(Products!D:D,MATCH(C39,Products!A:A,0)) -> 58 | N39: =CHOOSE(MONTH(D39),"Winter","Winter","Spring","Spring","Spring","Summer","Summer","Summer","Fall","Fall","Fall","Winter") -> Fall | O39: =IF(I39<20,"<20",IF(I39<40,"20-40",IF(I39<60,"40-60","60+"))) -> 20-40 | P39: =IF(COUNTIF(B:B,B39)>1,"Yes","No") -> Yes | Q39: =IF(F39="","No Code","Used Code") -> No Code
A40: 5163 | B40: C080 | C40: P16 | D40: 45825 | E40: Cash on Delivery | G40: =INDEX(Customers!B:B,MATCH(B40,Customers!A:A,0)) -> Blessing Moore | H40: =INDEX(Customers!E:E,MATCH(B40,Customers!A:A,0)) -> Female | I40: =INDEX(Customers!C:C,MATCH(B40,Customers!A:A,0)) -> 50 | J40: =INDEX(Customers!D:D,MATCH(B40,Customers!A:A,0)) -> Owerri | K40: =INDEX(Products!B:B,MATCH(C40,Products!A:A,0)) -> Accessories | L40: =INDEX(Products!C:C,MATCH(C40,Products!A:A,0)) -> Bangle Set | M40: =INDEX(Products!D:D,MATCH(C40,Products!A:A,0)) -> 22 | N40: =CHOOSE(MONTH(D40),"Winter","Winter","Spring","Spring","Spring","Summer","Summer","Summer","Fall","Fall","Fall","Winter") -> Summer | O40: =IF(I40<20,"<20",IF(I40<40,"20-40",IF(I40<60,"40-60","60+"))) -> 40-60 | P40: =IF(COUNTIF(B:B,B40)>1,"Yes","No") -> Yes | Q40: =IF(F40="","No Code","Used Code") -> No Code
A41: 5193 | B41: C097 | C41: P09 | D41: 46327 | E41: Debit Card | G41: =INDEX(Customers!B:B,MATCH(B41,Customers!A:A,0)) -> William Wilson | H41: =INDEX(Customers!E:E,MATCH(B41,Customers!A:A,0)) -> Male | I41: =INDEX(Customers!C:C,MATCH(B41,Customers!A:A,0)) -> 27 | J41: =INDEX(Customers!D:D,MATCH(B41,Customers!A:A,0)) -> Owerri | K41: =INDEX(Products!B:B,MATCH(C41,Products!A:A,0)) -> Clothing | L41: =INDEX(Products!C:C,MATCH(C41,Products!A:A,0)) -> Wrap Skirt | M41: =INDEX(Products!D:D,MATCH(C41,Products!A:A,0)) -> 42 | N41: =CHOOSE(MONTH(D41),"Winter","Winter","Spring","Spring","Spring","Summer","Summer","Summer","Fall","Fall","Fall","Winter") -> Fall | O41: =IF(I41<20,"<20",IF(I41<40,"20-40",IF(I41<60,"40-60","60+"))) -> 20-40 | P41: =IF(COUNTIF(B:B,B41)>1,"Yes","No") -> No | Q41: =IF(F41="","No Code","Used Code") -> No Code
A42: 5263 | B42: C127 | C42: P02 | D42: 46084 | E42: PayPal | G42: =INDEX(Customers!B:B,MATCH(B42,Customers!A:A,0)) -> Tunde Davis | H42: =INDEX(Customers!E:E,MATCH(B42,Customers!A:A,0)) -> Male | I42: =INDEX(Customers!C:C,MATCH(B42,Customers!A:A,0)) -> 57 | J42: =INDEX(Customers!D:D,MATCH(B42,Customers!A:A,0)) -> Abeokuta | K42: =INDEX(Products!B:B,MATCH(C42,Products!A:A,0)) -> Clothing | L42: =INDEX(Products!C:C,MATCH(C42,Products!A:A,0)) -> Denim Jacket | M42: =INDEX(Products!D:D,MATCH(C42,Products!A:A,0)) -> 95 | N42: =CHOOSE(MONTH(D42),"Winter","Winter","Spring","Spring","Spring","Summer","Summer","Summer","Fall","Fall","Fall","Winter") -> Spring | O42: =IF(I42<20,"<20",IF(I42<40,"20-40",IF(I42<60,"40-60","60+"))) -> 40-60 | P42: =IF(COUNTIF(B:B,B42)>1,"Yes","No") -> Yes | Q42: =IF(F42="","No Code","Used Code") -> No Code
A43: 5161 | B43: C078 | C43: P01 | D43: 45971 | E43: Cash on Delivery | F43: VIP20 | G43: =INDEX(Customers!B:B,MATCH(B43,Customers!A:A,0)) -> Nancy Moore | H43: =INDEX(Customers!E:E,MATCH(B43,Customers!A:A,0)) -> Female | I43: =INDEX(Customers!C:C,MATCH(B43,Customers!A:A,0)) -> 53 | J43: =INDEX(Customers!D:D,MATCH(B43,Customers!A:A,0)) -> Lagos | K43: =INDEX(Products!B:B,MATCH(C43,Products!A:A,0)) -> Clothing | L43: =INDEX(Products!C:C,MATCH(C43,Products!A:A,0)) -> Ankara Dress | M43: =INDEX(Products!D:D,MATCH(C43,Products!A:A,0)) -> 68 | N43: =CHOOSE(MONTH(D43),"Winter","Winter","Spring","Spring","Spring","Summer","Summer","Summer","Fall","Fall","Fall","Winter") -> Fall | O43: =IF(I43<20,"<20",IF(I43<40,"20-40",IF(I43<60,"40-60","60+"))) -> 40-60 | P43: =IF(COUNTIF(B:B,B43)>1,"Yes","No") -> Yes | Q43: =IF(F43="","No Code","Used Code") -> Used Code
A44: 5017 | B44: C007 | C44: P04 | D44: 46144 | E44: Card | G44: =INDEX(Customers!B:B,MATCH(B44,Customers!A:A,0)) -> David Ibrahim | H44: =INDEX(Customers!E:E,MATCH(B44,Customers!A:A,0)) -> Male | I44: =INDEX(Customers!C:C,MATCH(B44,Customers!A:A,0)) -> 20 | J44: =INDEX(Customers!D:D,MATCH(B44,Customers!A:A,0)) -> Owerri | K44: =INDEX(Products!B:B,MATCH(C44,Products!A:A,0)) -> Clothing | L44: =INDEX(Products!C:C,MATCH(C44,Products!A:A,0)) -> Maxi Gown | M44: =INDEX(Products!D:D,MATCH(C44,Products!A:A,0)) -> 120 | N44: =CHOOSE(MONTH(D44),"Winter","Winter","Spring","Spring","Spring","Summer","Summer","Summer","Fall","Fall","Fall","Winter") -> Spring | O44: =IF(I44<20,"<20",IF(I44<40,"20-40",IF(I44<60,"40-60","60+"))) -> 20-40 | P44: =IF(COUNTIF(B:B,B44)>1,"Yes","No") -> No | Q44: =IF(F44="","No Code","Used Code") -> No Code
A45: 5139 | B45: C066 | C45: P11 | D45: 46157 | E45: Card | F45: VIP20 | G45: =INDEX(Customers!B:B,MATCH(B45,Customers!A:A,0)) -> Amara Chukwu | H45: =INDEX(Customers!E:E,MATCH(B45,Customers!A:A,0)) -> Female | I45: =INDEX(Customers!C:C,MATCH(B45,Customers!A:A,0)) -> 59 | J45: =INDEX(Customers!D:D,MATCH(B45,Customers!A:A,0)) -> Abuja | K45: =INDEX(Products!B:B,MATCH(C45,Products!A:A,0)) -> Accessories | L45: =INDEX(Products!C:C,MATCH(C45,Products!A:A,0)) -> Beaded Necklace | M45: =INDEX(Products!D:D,MATCH(C45,Products!A:A,0)) -> 25 | N45: =CHOOSE(MONTH(D45),"Winter","Winter","Spring","Spring","Spring","Summer","Summer","Summer","Fall","Fall","Fall","Winter") -> Spring | O45: =IF(I45<20,"<20",IF(I45<40,"20-40",IF(I45<60,"40-60","60+"))) -> 40-60 | P45: =IF(COUNTIF(B:B,B45)>1,"Yes","No") -> No | Q45: =IF(F45="","No Code","Used Code") -> Used Code
A46: 5084 | B46: C039 | C46: P17 | D46: 46014 | E46: Bank Transfer | G46: =INDEX(Customers!B:B,MATCH(B46,Customers!A:A,0)) -> Grace Okafor | H46: =INDEX(Customers!E:E,MATCH(B46,Customers!A:A,0)) -> Female | I46: =INDEX(Customers!C:C,MATCH(B46,Customers!A:A,0)) -> 54 | J46: =INDEX(Customers!D:D,MATCH(B46,Customers!A:A,0)) -> Port Harcourt | K46: =INDEX(Products!B:B,MATCH(C46,Products!A:A,0)) -> Accessories | L46: =INDEX(Products!C:C,MATCH(C46,Products!A:A,0)) -> Ankle Boots | M46: =INDEX(Products!D:D,MATCH(C46,Products!A:A,0)) -> 110 | N46: =CHOOSE(MONTH(D46),"Winter","Winter","Spring","Spring","Spring","Summer","Summer","Summer","Fall","Fall","Fall","Winter") -> Winter | O46: =IF(I46<20,"<20",IF(I46<40,"20-40",IF(I46<60,"40-60","60+"))) -> 40-60 | P46: =IF(COUNTIF(B:B,B46)>1,"Yes","No") -> No | Q46: =IF(F46="","No Code","Used Code") -> No Code
A47: 5238 | B47: C118 | C47: P10 | D47: 45980 | E47: Card | F47: FLASH5 | G47: =INDEX(Customers!B:B,MATCH(B47,Customers!A:A,0)) -> Blessing Moore | H47: =INDEX(Customers!E:E,MATCH(B47,Customers!A:A,0)) -> Female | I47: =INDEX(Customers!C:C,MATCH(B47,Customers!A:A,0)) -> 18 | J47: =INDEX(Customers!D:D,MATCH(B47,Customers!A:A,0)) -> Kano | K47: =INDEX(Products!B:B,MATCH(C47,Products!A:A,0)) -> Clothing | L47: =INDEX(Products!C:C,MATCH(C47,Products!A:A,0)) -> Knit Sweater | M47: =INDEX(Products!D:D,MATCH(C47,Products!A:A,0)) -> 58 | N47: =CHOOSE(MONTH(D47),"Winter","Winter","Spring","Spring","Spring","Summer","Summer","Summer","Fall","Fall","Fall","Winter") -> Fall | O47: =IF(I47<20,"<20",IF(I47<40,"20-40",IF(I47<60,"40-60","60+"))) -> <20 | P47: =IF(COUNTIF(B:B,B47)>1,"Yes","No") -> Yes | Q47: =IF(F47="","No Code","Used Code") -> Used Code
A48: 5285 | B48: C134 | C48: P03 | D48: 45824 | E48: Debit Card | G48: =INDEX(Customers!B:B,MATCH(B48,Customers!A:A,0)) -> Adaeze Eze | H48: =INDEX(Customers!E:E,MATCH(B48,Customers!A:A,0)) -> Female | I48: =INDEX(Customers!C:C,MATCH(B48,Customers!A:A,0)) -> 18 | J48: =INDEX(Customers!D:D,MATCH(B48,Customers!A:A,0)) -> Kaduna | K48: =INDEX(Products!B:B,MATCH(C48,Products!A:A,0)) -> Clothing | L48: =INDEX(Products!C:C,MATCH(C48,Products!A:A,0)) -> Silk Blouse | M48: =INDEX(Products!D:D,MATCH(C48,Products!A:A,0)) -> 54 | N48: =CHOOSE(MONTH(D48),"Winter","Winter","Spring","Spring","Spring","Summer","Summer","Summer","Fall","Fall","Fall","Winter") -> Summer | O48: =IF(I48<20,"<20",IF(I48<40,"20-40",IF(I48<60,"40-60","60+"))) -> <20 | P48: =IF(COUNTIF(B:B,B48)>1,"Yes","No") -> Yes | Q48: =IF(F48="","No Code","Used Code") -> No Code
A49: 5051 | B49: C022 | C49: P02 | D49: 45959 | E49: Bank Transfer | G49: =INDEX(Customers!B:B,MATCH(B49,Customers!A:A,0)) -> James Smith | H49: =INDEX(Customers!E:E,MATCH(B49,Customers!A:A,0)) -> Male | I49: =INDEX(Customers!C:C,MATCH(B49,Customers!A:A,0)) -> 37 | J49: =INDEX(Customers!D:D,MATCH(B49,Customers!A:A,0)) -> Abeokuta | K49: =INDEX(Products!B:B,MATCH(C49,Products!A:A,0)) -> Clothing | L49: =INDEX(Products!C:C,MATCH(C49,Products!A:A,0)) -> Denim Jacket | M49: =INDEX(Products!D:D,MATCH(C49,Products!A:A,0)) -> 95 | N49: =CHOOSE(MONTH(D49),"Winter","Winter","Spring","Spring","Spring","Summer","Summer","Summer","Fall","Fall","Fall","Winter") -> Fall | O49: =IF(I49<20,"<20",IF(I49<40,"20-40",IF(I49<60,"40-60","60+"))) -> 20-40 | P49: =IF(COUNTIF(B:B,B49)>1,"Yes","No") -> Yes | Q49: =IF(F49="","No Code","Used Code") -> No Code
A50: 5260 | B50: C127 | C50: P05 | D50: 46140 | E50: PayPal | G50: =INDEX(Customers!B:B,MATCH(B50,Customers!A:A,0)) -> Tunde Davis | H50: =INDEX(Customers!E:E,MATCH(B50,Customers!A:A,0)) -> Male | I50: =INDEX(Customers!C:C,MATCH(B50,Customers!A:A,0)) -> 57 | J50: =INDEX(Customers!D:D,MATCH(B50,Customers!A:A,0)) -> Abeokuta | K50: =INDEX(Products!B:B,MATCH(C50,Products!A:A,0)) -> Clothing | L50: =INDEX(Products!C:C,MATCH(C50,Products!A:A,0)) -> Linen Trousers | M50: =INDEX(Products!D:D,MATCH(C50,Products!A:A,0)) -> 47 | N50: =CHOOSE(MONTH(D50),"Winter","Winter","Spring","Spring","Spring","Summer","Summer","Summer","Fall","Fall","Fall","Winter") -> Spring | O50: =IF(I50<20,"<20",IF(I50<40,"20-40",IF(I50<60,"40-60","60+"))) -> 40-60 | P50: =IF(COUNTIF(B:B,B50)>1,"Yes","No") -> Yes | Q50: =IF(F50="","No Code","Used Code") -> No Code
A51: 5173 | B51: C087 | C51: P07 | D51: 45993 | E51: Card | F51: SEASON15 | G51: =INDEX(Customers!B:B,MATCH(B51,Customers!A:A,0)) -> Tunde Eze | H51: =INDEX(Customers!E:E,MATCH(B51,Customers!A:A,0)) -> Male | I51: =INDEX(Customers!C:C,MATCH(B51,Customers!A:A,0)) -> 26 | J51: =INDEX(Customers!D:D,MATCH(B51,Customers!A:A,0)) -> Kaduna | K51: =INDEX(Products!B:B,MATCH(C51,Products!A:A,0)) -> Clothing | L51: =INDEX(Products!C:C,MATCH(C51,Products!A:A,0)) -> Blazer | M51: =INDEX(Products!D:D,MATCH(C51,Products!A:A,0)) -> 135 | N51: =CHOOSE(MONTH(D51),"Winter","Winter","Spring","Spring","Spring","Summer","Summer","Summer","Fall","Fall","Fall","Winter") -> Winter | O51: =IF(I51<20,"<20",IF(I51<40,"20-40",IF(I51<60,"40-60","60+"))) -> 20-40 | P51: =IF(COUNTIF(B:B,B51)>1,"Yes","No") -> Yes | Q51: =IF(F51="","No Code","Used Code") -> Used Code
A52: 5164 | B52: C080 | C52: P05 | D52: 45938 | E52: Debit Card | G52: =INDEX(Customers!B:B,MATCH(B52,Customers!A:A,0)) -> Blessing Moore | H52: =INDEX(Customers!E:E,MATCH(B52,Customers!A:A,0)) -> Female | I52: =INDEX(Customers!C:C,MATCH(B52,Customers!A:A,0)) -> 50 | J52: =INDEX(Customers!D:D,MATCH(B52,Customers!A:A,0)) -> Owerri | K52: =INDEX(Products!B:B,MATCH(C52,Products!A:A,0)) -> Clothing | L52: =INDEX(Products!C:C,MATCH(C52,Products!A:A,0)) -> Linen Trousers | M52: =INDEX(Products!D:D,MATCH(C52,Products!A:A,0)) -> 47 | N52: =CHOOSE(MONTH(D52),"Winter","Winter","Spring","Spring","Spring","Summer","Summer","Summer","Fall","Fall","Fall","Winter") -> Fall | O52: =IF(I52<20,"<20",IF(I52<40,"20-40",IF(I52<60,"40-60","60+"))) -> 40-60 | P52: =IF(COUNTIF(B:B,B52)>1,"Yes","No") -> Yes | Q52: =IF(F52="","No Code","Used Code") -> No Code
A53: 5294 | B53: C139 | C53: P03 | D53: 46081 | E53: Bank Transfer | F53: VIP20 | G53: =INDEX(Customers!B:B,MATCH(B53,Customers!A:A,0)) -> Daniel White | H53: =INDEX(Customers!E:E,MATCH(B53,Customers!A:A,0)) -> Male | I53: =INDEX(Customers!C:C,MATCH(B53,Customers!A:A,0)) -> 20 | J53: =INDEX(Customers!D:D,MATCH(B53,Customers!A:A,0)) -> Uyo | K53: =INDEX(Products!B:B,MATCH(C53,Products!A:A,0)) -> Clothing | L53: =INDEX(Products!C:C,MATCH(C53,Products!A:A,0)) -> Silk Blouse | M53: =INDEX(Products!D:D,MATCH(C53,Products!A:A,0)) -> 54 | N53: =CHOOSE(MONTH(D53),"Winter","Winter","Spring","Spring","Spring","Summer","Summer","Summer","Fall","Fall","Fall","Winter") -> Winter | O53: =IF(I53<20,"<20",IF(I53<40,"20-40",IF(I53<60,"40-60","60+"))) -> 20-40 | P53: =IF(COUNTIF(B:B,B53)>1,"Yes","No") -> Yes | Q53: =IF(F53="","No Code","Used Code") -> Used Code
A54: 5244 | B54: C121 | C54: P17 | D54: 46155 | E54: Card | G54: =INDEX(Customers!B:B,MATCH(B54,Customers!A:A,0)) -> Chioma Wilson | H54: =INDEX(Customers!E:E,MATCH(B54,Customers!A:A,0)) -> Female | I54: =INDEX(Customers!C:C,MATCH(B54,Customers!A:A,0)) -> 23 | J54: =INDEX(Customers!D:D,MATCH(B54,Customers!A:A,0)) -> Kaduna | K54: =INDEX(Products!B:B,MATCH(C54,Products!A:A,0)) -> Accessories | L54: =INDEX(Products!C:C,MATCH(C54,Products!A:A,0)) -> Ankle Boots | M54: =INDEX(Products!D:D,MATCH(C54,Products!A:A,0)) -> 110 | N54: =CHOOSE(MONTH(D54),"Winter","Winter","Spring","Spring","Spring","Summer","Summer","Summer","Fall","Fall","Fall","Winter") -> Spring | O54: =IF(I54<20,"<20",IF(I54<40,"20-40",IF(I54<60,"40-60","60+"))) -> 20-40 | P54: =IF(COUNTIF(B:B,B54)>1,"Yes","No") -> Yes | Q54: =IF(F54="","No Code","Used Code") -> No Code
A55: 5245 | B55: C121 | C55: P18 | D55: 45973 | E55: PayPal | G55: =INDEX(Customers!B:B,MATCH(B55,Customers!A:A,0)) -> Chioma Wilson | H55: =INDEX(Customers!E:E,MATCH(B55,Customers!A:A,0)) -> Female | I55: =INDEX(Customers!C:C,MATCH(B55,Customers!A:A,0)) -> 23 | J55: =INDEX(Customers!D:D,MATCH(B55,Customers!A:A,0)) -> Kaduna | K55: =INDEX(Products!B:B,MATCH(C55,Products!A:A,0)) -> Accessories | L55: =INDEX(Products!C:C,MATCH(C55,Products!A:A,0)) -> Clutch Purse | M55: =INDEX(Products!D:D,MATCH(C55,Products!A:A,0)) -> 48 | N55: =CHOOSE(MONTH(D55),"Winter","Winter","Spring","Spring","Spring","Summer","Summer","Summer","Fall","Fall","Fall","Winter") -> Fall | O55: =IF(I55<20,"<20",IF(I55<40,"20-40",IF(I55<60,"40-60","60+"))) -> 20-40 | P55: =IF(COUNTIF(B:B,B55)>1,"Yes","No") -> Yes | Q55: =IF(F55="","No Code","Used Code") -> No Code
A56: 5174 | B56: C087 | C56: P05 | D56: 45813 | E56: Bank Transfer | F56: VIP20 | G56: =INDEX(Customers!B:B,MATCH(B56,Customers!A:A,0)) -> Tunde Eze | H56: =INDEX(Customers!E:E,MATCH(B56,Customers!A:A,0)) -> Male | I56: =INDEX(Customers!C:C,MATCH(B56,Customers!A:A,0)) -> 26 | J56: =INDEX(Customers!D:D,MATCH(B56,Customers!A:A,0)) -> Kaduna | K56: =INDEX(Products!B:B,MATCH(C56,Products!A:A,0)) -> Clothing | L56: =INDEX(Products!C:C,MATCH(C56,Products!A:A,0)) -> Linen Trousers | M56: =INDEX(Products!D:D,MATCH(C56,Products!A:A,0)) -> 47 | N56: =CHOOSE(MONTH(D56),"Winter","Winter","Spring","Spring","Spring","Summer","Summer","Summer","Fall","Fall","Fall","Winter") -> Summer | O56: =IF(I56<20,"<20",IF(I56<40,"20-40",IF(I56<60,"40-60","60+"))) -> 20-40 | P56: =IF(COUNTIF(B:B,B56)>1,"Yes","No") -> Yes | Q56: =IF(F56="","No Code","Used Code") -> Used Code
A57: 5150 | B57: C074 | C57: P10 | D57: 45983 | E57: Cash on Delivery | F57: FLASH5 | G57: =INDEX(Customers!B:B,MATCH(B57,Customers!A:A,0)) -> Ngozi Williams | H57: =INDEX(Customers!E:E,MATCH(B57,Customers!A:A,0)) -> Female | I57: =INDEX(Customers!C:C,MATCH(B57,Customers!A:A,0)) -> 27 | J57: =INDEX(Customers!D:D,MATCH(B57,Customers!A:A,0)) -> Kaduna | K57: =INDEX(Products!B:B,MATCH(C57,Products!A:A,0)) -> Clothing | L57: =INDEX(Products!C:C,MATCH(C57,Products!A:A,0)) -> Knit Sweater | M57: =INDEX(Products!D:D,MATCH(C57,Products!A:A,0)) -> 58 | N57: =CHOOSE(MONTH(D57),"Winter","Winter","Spring","Spring","Spring","Summer","Summer","Summer","Fall","Fall","Fall","Winter") -> Fall | O57: =IF(I57<20,"<20",IF(I57<40,"20-40",IF(I57<60,"40-60","60+"))) -> 20-40 | P57: =IF(COUNTIF(B:B,B57)>1,"Yes","No") -> Yes | Q57: =IF(F57="","No Code","Used Code") -> Used Code
A58: 5065 | B58: C031 | C58: P12 | D58: 45936 | E58: PayPal | F58: SEASON15 | G58: =INDEX(Customers!B:B,MATCH(B58,Customers!A:A,0)) -> Aisha Garba | H58: =INDEX(Customers!E:E,MATCH(B58,Customers!A:A,0)) -> Female | I58: =INDEX(Customers!C:C,MATCH(B58,Customers!A:A,0)) -> 32 | J58: =INDEX(Customers!D:D,MATCH(B58,Customers!A:A,0)) -> Lagos | K58: =INDEX(Products!B:B,MATCH(C58,Products!A:A,0)) -> Accessories | L58: =INDEX(Products!C:C,MATCH(C58,Products!A:A,0)) -> Leather Handbag | M58: =INDEX(Products!D:D,MATCH(C58,Products!A:A,0)) -> 145 | N58: =CHOOSE(MONTH(D58),"Winter","Winter","Spring","Spring","Spring","Summer","Summer","Summer","Fall","Fall","Fall","Winter") -> Fall | O58: =IF(I58<20,"<20",IF(I58<40,"20-40",IF(I58<60,"40-60","60+"))) -> 20-40 | P58: =IF(COUNTIF(B:B,B58)>1,"Yes","No") -> Yes | Q58: =IF(F58="","No Code","Used Code") -> Used Code
A59: 5248 | B59: C122 | C59: P16 | D59: 46172 | E59: Cash on Delivery | F59: FLASH5 | G59: =INDEX(Customers!B:B,MATCH(B59,Customers!A:A,0)) -> Yusuf Thomas | H59: =INDEX(Customers!E:E,MATCH(B59,Customers!A:A,0)) -> Male | I59: =INDEX(Customers!C:C,MATCH(B59,Customers!A:A,0)) -> 30 | J59: =INDEX(Customers!D:D,MATCH(B59,Customers!A:A,0)) -> Ibadan | K59: =INDEX(Products!B:B,MATCH(C59,Products!A:A,0)) -> Accessories | L59: =INDEX(Products!C:C,MATCH(C59,Products!A:A,0)) -> Bangle Set | M59: =INDEX(Products!D:D,MATCH(C59,Products!A:A,0)) -> 22 | N59: =CHOOSE(MONTH(D59),"Winter","Winter","Spring","Spring","Spring","Summer","Summer","Summer","Fall","Fall","Fall","Winter") -> Spring | O59: =IF(I59<20,"<20",IF(I59<40,"20-40",IF(I59<60,"40-60","60+"))) -> 20-40 | P59: =IF(COUNTIF(B:B,B59)>1,"Yes","No") -> Yes | Q59: =IF(F59="","No Code","Used Code") -> Used Code
A60: 5010 | B60: C003 | C60: P04 | D60: 46070 | E60: PayPal | G60: =INDEX(Customers!B:B,MATCH(B60,Customers!A:A,0)) -> Nancy Brown | H60: =INDEX(Customers!E:E,MATCH(B60,Customers!A:A,0)) -> Female | I60: =INDEX(Customers!C:C,MATCH(B60,Customers!A:A,0)) -> 20 | J60: =INDEX(Customers!D:D,MATCH(B60,Customers!A:A,0)) -> Abuja | K60: =INDEX(Products!B:B,MATCH(C60,Products!A:A,0)) -> Clothing | L60: =INDEX(Products!C:C,MATCH(C60,Products!A:A,0)) -> Maxi Gown | M60: =INDEX(Products!D:D,MATCH(C60,Products!A:A,0)) -> 120 | N60: =CHOOSE(MONTH(D60),"Winter","Winter","Spring","Spring","Spring","Summer","Summer","Summer","Fall","Fall","Fall","Winter") -> Winter | O60: =IF(I60<20,"<20",IF(I60<40,"20-40",IF(I60<60,"40-60","60+"))) -> 20-40 | P60: =IF(COUNTIF(B:B,B60)>1,"Yes","No") -> Yes | Q60: =IF(F60="","No Code","Used Code") -> No Code
A61: 5027 | B61: C011 | C61: P13 | D61: 46040 | E61: Cash on Delivery | F61: WELCOME10 | G61: =INDEX(Customers!B:B,MATCH(B61,Customers!A:A,0)) -> Nkechi Bello | H61: =INDEX(Customers!E:E,MATCH(B61,Customers!A:A,0)) -> Female | I61: =INDEX(Customers!C:C,MATCH(B61,Customers!A:A,0)) -> 53 | J61: =INDEX(Customers!D:D,MATCH(B61,Customers!A:A,0)) -> Warri | K61: =INDEX(Products!B:B,MATCH(C61,Products!A:A,0)) -> Accessories | L61: =INDEX(Products!C:C,MATCH(C61,Products!A:A,0)) -> Sunglasses | M61: =INDEX(Products!D:D,MATCH(C61,Products!A:A,0)) -> 38 | N61: =CHOOSE(MONTH(D61),"Winter","Winter","Spring","Spring","Spring","Summer","Summer","Summer","Fall","Fall","Fall","Winter") -> Winter | O61: =IF(I61<20,"<20",IF(I61<40,"20-40",IF(I61<60,"40-60","60+"))) -> 40-60 | P61: =IF(COUNTIF(B:B,B61)>1,"Yes","No") -> Yes | Q61: =IF(F61="","No Code","Used Code") -> Used Code
A62: 5112 | B62: C055 | C62: P17 | D62: 46161 | E62: PayPal | G62: =INDEX(Customers!B:B,MATCH(B62,Customers!A:A,0)) -> Brian Chukwu | H62: =INDEX(Customers!E:E,MATCH(B62,Customers!A:A,0)) -> Male | I62: =INDEX(Customers!C:C,MATCH(B62,Customers!A:A,0)) -> 40 | J62: =INDEX(Customers!D:D,MATCH(B62,Customers!A:A,0)) -> Enugu | K62: =INDEX(Products!B:B,MATCH(C62,Products!A:A,0)) -> Accessories | L62: =INDEX(Products!C:C,MATCH(C62,Products!A:A,0)) -> Ankle Boots | M62: =INDEX(Products!D:D,MATCH(C62,Products!A:A,0)) -> 110 | N62: =CHOOSE(MONTH(D62),"Winter","Winter","Spring","Spring","Spring","Summer","Summer","Summer","Fall","Fall","Fall","Winter") -> Spring | O62: =IF(I62<20,"<20",IF(I62<40,"20-40",IF(I62<60,"40-60","60+"))) -> 40-60 | P62: =IF(COUNTIF(B:B,B62)>1,"Yes","No") -> Yes | Q62: =IF(F62="","No Code","Used Code") -> No Code
A63: 5216 | B63: C107 | C63: P12 | D63: 45818 | E63: PayPal | F63: VIP20 | G63: =INDEX(Customers!B:B,MATCH(B63,Customers!A:A,0)) -> Blessing Nwosu | H63: =INDEX(Customers!E:E,MATCH(B63,Customers!A:A,0)) -> Female | I63: =INDEX(Customers!C:C,MATCH(B63,Customers!A:A,0)) -> 19 | J63: =INDEX(Customers!D:D,MATCH(B63,Customers!A:A,0)) -> Kano | K63: =INDEX(Products!B:B,MATCH(C63,Products!A:A,0)) -> Accessories | L63: =INDEX(Products!C:C,MATCH(C63,Products!A:A,0)) -> Leather Handbag | M63: =INDEX(Products!D:D,MATCH(C63,Products!A:A,0)) -> 145 | N63: =CHOOSE(MONTH(D63),"Winter","Winter","Spring","Spring","Spring","Summer","Summer","Summer","Fall","Fall","Fall","Winter") -> Summer | O63: =IF(I63<20,"<20",IF(I63<40,"20-40",IF(I63<60,"40-60","60+"))) -> <20 | P63: =IF(COUNTIF(B:B,B63)>1,"Yes","No") -> No | Q63: =IF(F63="","No Code","Used Code") -> Used Code
A64: 5137 | B64: C065 | C64: P03 | D64: 45879 | E64: Cash on Delivery | F64: WELCOME10 | G64: =INDEX(Customers!B:B,MATCH(B64,Customers!A:A,0)) -> Tunde Suleiman | H64: =INDEX(Customers!E:E,MATCH(B64,Customers!A:A,0)) -> Male | I64: =INDEX(Customers!C:C,MATCH(B64,Customers!A:A,0)) -> 53 | J64: =INDEX(Customers!D:D,MATCH(B64,Customers!A:A,0)) -> Port Harcourt | K64: =INDEX(Products!B:B,MATCH(C64,Products!A:A,0)) -> Clothing | L64: =INDEX(Products!C:C,MATCH(C64,Products!A:A,0)) -> Silk Blouse | M64: =INDEX(Products!D:D,MATCH(C64,Products!A:A,0)) -> 54 | N64: =CHOOSE(MONTH(D64),"Winter","Winter","Spring","Spring","Spring","Summer","Summer","Summer","Fall","Fall","Fall","Winter") -> Summer | O64: =IF(I64<20,"<20",IF(I64<40,"20-40",IF(I64<60,"40-60","60+"))) -> 40-60 | P64: =IF(COUNTIF(B:B,B64)>1,"Yes","No") -> Yes | Q64: =IF(F64="","No Code","Used Code") -> Used Code
A65: 5076 | B65: C034 | C65: P17 | D65: 45857 | E65: PayPal | G65: =INDEX(Customers!B:B,MATCH(B65,Customers!A:A,0)) -> Tunde Jackson | H65: =INDEX(Customers!E:E,MATCH(B65,Customers!A:A,0)) -> Male | I65: =INDEX(Customers!C:C,MATCH(B65,Customers!A:A,0)) -> 50 | J65: =INDEX(Customers!D:D,MATCH(B65,Customers!A:A,0)) -> Uyo | K65: =INDEX(Products!B:B,MATCH(C65,Products!A:A,0)) -> Accessories | L65: =INDEX(Products!C:C,MATCH(C65,Products!A:A,0)) -> Ankle Boots | M65: =INDEX(Products!D:D,MATCH(C65,Products!A:A,0)) -> 110 | N65: =CHOOSE(MONTH(D65),"Winter","Winter","Spring","Spring","Spring","Summer","Summer","Summer","Fall","Fall","Fall","Winter") -> Summer | O65: =IF(I65<20,"<20",IF(I65<40,"20-40",IF(I65<60,"40-60","60+"))) -> 40-60 | P65: =IF(COUNTIF(B:B,B65)>1,"Yes","No") -> Yes | Q65: =IF(F65="","No Code","Used Code") -> No Code
A66: 5070 | B66: C032 | C66: P10 | D66: 46017 | E66: Cash on Delivery | F66: WELCOME10 | G66: =INDEX(Customers!B:B,MATCH(B66,Customers!A:A,0)) -> Musa Williams | H66: =INDEX(Customers!E:E,MATCH(B66,Customers!A:A,0)) -> Male | I66: =INDEX(Customers!C:C,MATCH(B66,Customers!A:A,0)) -> 34 | J66: =INDEX(Customers!D:D,MATCH(B66,Customers!A:A,0)) -> Kano | K66: =INDEX(Products!B:B,MATCH(C66,Products!A:A,0)) -> Clothing | L66: =INDEX(Products!C:C,MATCH(C66,Products!A:A,0)) -> Knit Sweater | M66: =INDEX(Products!D:D,MATCH(C66,Products!A:A,0)) -> 58 | N66: =CHOOSE(MONTH(D66),"Winter","Winter","Spring","Spring","Spring","Summer","Summer","Summer","Fall","Fall","Fall","Winter") -> Winter | O66: =IF(I66<20,"<20",IF(I66<40,"20-40",IF(I66<60,"40-60","60+"))) -> 20-40 | P66: =IF(COUNTIF(B:B,B66)>1,"Yes","No") -> Yes | Q66: =IF(F66="","No Code","Used Code") -> Used Code
A67: 5275 | B67: C132 | C67: P13 | D67: 45891 | E67: PayPal | F67: WELCOME10 | G67: =INDEX(Customers!B:B,MATCH(B67,Customers!A:A,0)) -> Michael Wilson | H67: =INDEX(Customers!E:E,MATCH(B67,Customers!A:A,0)) -> Male | I67: =INDEX(Customers!C:C,MATCH(B67,Customers!A:A,0)) -> 46 | J67: =INDEX(Customers!D:D,MATCH(B67,Customers!A:A,0)) -> Owerri | K67: =INDEX(Products!B:B,MATCH(C67,Products!A:A,0)) -> Accessories | L67: =INDEX(Products!C:C,MATCH(C67,Products!A:A,0)) -> Sunglasses | M67: =INDEX(Products!D:D,MATCH(C67,Products!A:A,0)) -> 38 | N67: =CHOOSE(MONTH(D67),"Winter","Winter","Spring","Spring","Spring","Summer","Summer","Summer","Fall","Fall","Fall","Winter") -> Summer | O67: =IF(I67<20,"<20",IF(I67<40,"20-40",IF(I67<60,"40-60","60+"))) -> 40-60 | P67: =IF(COUNTIF(B:B,B67)>1,"Yes","No") -> Yes | Q67: =IF(F67="","No Code","Used Code") -> Used Code
A68: 5237 | B68: C118 | C68: P20 | D68: 45962 | E68: PayPal | F68: SEASON15 | G68: =INDEX(Customers!B:B,MATCH(B68,Customers!A:A,0)) -> Blessing Moore | H68: =INDEX(Customers!E:E,MATCH(B68,Customers!A:A,0)) -> Female | I68: =INDEX(Customers!C:C,MATCH(B68,Customers!A:A,0)) -> 18 | J68: =INDEX(Customers!D:D,MATCH(B68,Customers!A:A,0)) -> Kano | K68: =INDEX(Products!B:B,MATCH(C68,Products!A:A,0)) -> Accessories | L68: =INDEX(Products!C:C,MATCH(C68,Products!A:A,0)) -> Waist Belt | M68: =INDEX(Products!D:D,MATCH(C68,Products!A:A,0)) -> 33 | N68: =CHOOSE(MONTH(D68),"Winter","Winter","Spring","Spring","Spring","Summer","Summer","Summer","Fall","Fall","Fall","Winter") -> Fall | O68: =IF(I68<20,"<20",IF(I68<40,"20-40",IF(I68<60,"40-60","60+"))) -> <20 | P68: =IF(COUNTIF(B:B,B68)>1,"Yes","No") -> Yes | Q68: =IF(F68="","No Code","Used Code") -> Used Code
A69: 5086 | B69: C040 | C69: P11 | D69: 46069 | E69: PayPal | G69: =INDEX(Customers!B:B,MATCH(B69,Customers!A:A,0)) -> Nkechi Okoro | H69: =INDEX(Customers!E:E,MATCH(B69,Customers!A:A,0)) -> Female | I69: =INDEX(Customers!C:C,MATCH(B69,Customers!A:A,0)) -> 19 | J69: =INDEX(Customers!D:D,MATCH(B69,Customers!A:A,0)) -> Abuja | K69: =INDEX(Products!B:B,MATCH(C69,Products!A:A,0)) -> Accessories | L69: =INDEX(Products!C:C,MATCH(C69,Products!A:A,0)) -> Beaded Necklace | M69: =INDEX(Products!D:D,MATCH(C69,Products!A:A,0)) -> 25 | N69: =CHOOSE(MONTH(D69),"Winter","Winter","Spring","Spring","Spring","Summer","Summer","Summer","Fall","Fall","Fall","Winter") -> Winter | O69: =IF(I69<20,"<20",IF(I69<40,"20-40",IF(I69<60,"40-60","60+"))) -> <20 | P69: =IF(COUNTIF(B:B,B69)>1,"Yes","No") -> Yes | Q69: =IF(F69="","No Code","Used Code") -> No Code
A70: 5280 | B70: C133 | C70: P04 | D70: 46063 | E70: PayPal | G70: =INDEX(Customers!B:B,MATCH(B70,Customers!A:A,0)) -> Amara Thomas | H70: =INDEX(Customers!E:E,MATCH(B70,Customers!A:A,0)) -> Female | I70: =INDEX(Customers!C:C,MATCH(B70,Customers!A:A,0)) -> 39 | J70: =INDEX(Customers!D:D,MATCH(B70,Customers!A:A,0)) -> Abeokuta | K70: =INDEX(Products!B:B,MATCH(C70,Products!A:A,0)) -> Clothing | L70: =INDEX(Products!C:C,MATCH(C70,Products!A:A,0)) -> Maxi Gown | M70: =INDEX(Products!D:D,MATCH(C70,Products!A:A,0)) -> 120 | N70: =CHOOSE(MONTH(D70),"Winter","Winter","Spring","Spring","Spring","Summer","Summer","Summer","Fall","Fall","Fall","Winter") -> Winter | O70: =IF(I70<20,"<20",IF(I70<40,"20-40",IF(I70<60,"40-60","60+"))) -> 20-40 | P70: =IF(COUNTIF(B:B,B70)>1,"Yes","No") -> Yes | Q70: =IF(F70="","No Code","Used Code") -> No Code
A71: 5159 | B71: C078 | C71: P01 | D71: 46141 | E71: PayPal | G71: =INDEX(Customers!B:B,MATCH(B71,Customers!A:A,0)) -> Nancy Moore | H71: =INDEX(Customers!E:E,MATCH(B71,Customers!A:A,0)) -> Female | I71: =INDEX(Customers!C:C,MATCH(B71,Customers!A:A,0)) -> 53 | J71: =INDEX(Customers!D:D,MATCH(B71,Customers!A:A,0)) -> Lagos | K71: =INDEX(Products!B:B,MATCH(C71,Products!A:A,0)) -> Clothing | L71: =INDEX(Products!C:C,MATCH(C71,Products!A:A,0)) -> Ankara Dress | M71: =INDEX(Products!D:D,MATCH(C71,Products!A:A,0)) -> 68 | N71: =CHOOSE(MONTH(D71),"Winter","Winter","Spring","Spring","Spring","Summer","Summer","Summer","Fall","Fall","Fall","Winter") -> Spring | O71: =IF(I71<20,"<20",IF(I71<40,"20-40",IF(I71<60,"40-60","60+"))) -> 40-60 | P71: =IF(COUNTIF(B:B,B71)>1,"Yes","No") -> Yes | Q71: =IF(F71="","No Code","Used Code") -> No Code
A72: 5001 | B72: C001 | C72: P18 | D72: 46141 | E72: Bank Transfer | F72: SEASON15 | G72: =INDEX(Customers!B:B,MATCH(B72,Customers!A:A,0)) -> Tunde Wilson | H72: =INDEX(Customers!E:E,MATCH(B72,Customers!A:A,0)) -> Male | I72: =INDEX(Customers!C:C,MATCH(B72,Customers!A:A,0)) -> 59 | J72: =INDEX(Customers!D:D,MATCH(B72,Customers!A:A,0)) -> Lagos | K72: =INDEX(Products!B:B,MATCH(C72,Products!A:A,0)) -> Accessories | L72: =INDEX(Products!C:C,MATCH(C72,Products!A:A,0)) -> Clutch Purse | M72: =INDEX(Products!D:D,MATCH(C72,Products!A:A,0)) -> 48 | N72: =CHOOSE(MONTH(D72),"Winter","Winter","Spring","Spring","Spring","Summer","Summer","Summer","Fall","Fall","Fall","Winter") -> Spring | O72: =IF(I72<20,"<20",IF(I72<40,"20-40",IF(I72<60,"40-60","60+"))) -> 40-60 | P72: =IF(COUNTIF(B:B,B72)>1,"Yes","No") -> Yes | Q72: =IF(F72="","No Code","Used Code") -> Used Code
A73: 5151 | B73: C074 | C73: P17 | D73: 45820 | E73: Bank Transfer | G73: =INDEX(Customers!B:B,MATCH(B73,Customers!A:A,0)) -> Ngozi Williams | H73: =INDEX(Customers!E:E,MATCH(B73,Customers!A:A,0)) -> Female | I73: =INDEX(Customers!C:C,MATCH(B73,Customers!A:A,0)) -> 27 | J73: =INDEX(Customers!D:D,MATCH(B73,Customers!A:A,0)) -> Kaduna | K73: =INDEX(Products!B:B,MATCH(C73,Products!A:A,0)) -> Accessories | L73: =INDEX(Products!C:C,MATCH(C73,Products!A:A,0)) -> Ankle Boots | M73: =INDEX(Products!D:D,MATCH(C73,Products!A:A,0)) -> 110 | N73: =CHOOSE(MONTH(D73),"Winter","Winter","Spring","Spring","Spring","Summer","Summer","Summer","Fall","Fall","Fall","Winter") -> Summer | O73: =IF(I73<20,"<20",IF(I73<40,"20-40",IF(I73<60,"40-60","60+"))) -> 20-40 | P73: =IF(COUNTIF(B:B,B73)>1,"Yes","No") -> Yes | Q73: =IF(F73="","No Code","Used Code") -> No Code
A74: 5021 | B74: C008 | C74: P14 | D74: 45811 | E74: Card | G74: =INDEX(Customers!B:B,MATCH(B74,Customers!A:A,0)) -> Rita Abubakar | H74: =INDEX(Customers!E:E,MATCH(B74,Customers!A:A,0)) -> Female | I74: =INDEX(Customers!C:C,MATCH(B74,Customers!A:A,0)) -> 27 | J74: =INDEX(Customers!D:D,MATCH(B74,Customers!A:A,0)) -> Owerri | K74: =INDEX(Products!B:B,MATCH(C74,Products!A:A,0)) -> Accessories | L74: =INDEX(Products!C:C,MATCH(C74,Products!A:A,0)) -> Hair Scarf | M74: =INDEX(Products!D:D,MATCH(C74,Products!A:A,0)) -> 15 | N74: =CHOOSE(MONTH(D74),"Winter","Winter","Spring","Spring","Spring","Summer","Summer","Summer","Fall","Fall","Fall","Winter") -> Summer | O74: =IF(I74<20,"<20",IF(I74<40,"20-40",IF(I74<60,"40-60","60+"))) -> 20-40 | P74: =IF(COUNTIF(B:B,B74)>1,"Yes","No") -> Yes | Q74: =IF(F74="","No Code","Used Code") -> No Code
A75: 5178 | B75: C089 | C75: P18 | D75: 46065 | E75: Debit Card | F75: FLASH5 | G75: =INDEX(Customers!B:B,MATCH(B75,Customers!A:A,0)) -> Sarah Jackson | H75: =INDEX(Customers!E:E,MATCH(B75,Customers!A:A,0)) -> Female | I75: =INDEX(Customers!C:C,MATCH(B75,Customers!A:A,0)) -> 45 | J75: =INDEX(Customers!D:D,MATCH(B75,Customers!A:A,0)) -> Unknown | K75: =INDEX(Products!B:B,MATCH(C75,Products!A:A,0)) -> Accessories | L75: =INDEX(Products!C:C,MATCH(C75,Products!A:A,0)) -> Clutch Purse | M75: =INDEX(Products!D:D,MATCH(C75,Products!A:A,0)) -> 48 | N75: =CHOOSE(MONTH(D75),"Winter","Winter","Spring","Spring","Spring","Summer","Summer","Summer","Fall","Fall","Fall","Winter") -> Winter | O75: =IF(I75<20,"<20",IF(I75<40,"20-40",IF(I75<60,"40-60","60+"))) -> 40-60 | P75: =IF(COUNTIF(B:B,B75)>1,"Yes","No") -> Yes | Q75: =IF(F75="","No Code","Used Code") -> Used Code
A76: 5217 | B76: C108 | C76: P16 | D76: 45947 | E76: Bank Transfer | F76: WELCOME10 | G76: =INDEX(Customers!B:B,MATCH(B76,Customers!A:A,0)) -> Amara Okafor | H76: =INDEX(Customers!E:E,MATCH(B76,Customers!A:A,0)) -> Female | I76: =INDEX(Customers!C:C,MATCH(B76,Customers!A:A,0)) -> 50 | J76: =INDEX(Customers!D:D,MATCH(B76,Customers!A:A,0)) -> Owerri | K76: =INDEX(Products!B:B,MATCH(C76,Products!A:A,0)) -> Accessories | L76: =INDEX(Products!C:C,MATCH(C76,Products!A:A,0)) -> Bangle Set | M76: =INDEX(Products!D:D,MATCH(C76,Products!A:A,0)) -> 22 | N76: =CHOOSE(MONTH(D76),"Winter","Winter","Spring","Spring","Spring","Summer","Summer","Summer","Fall","Fall","Fall","Winter") -> Fall | O76: =IF(I76<20,"<20",IF(I76<40,"20-40",IF(I76<60,"40-60","60+"))) -> 40-60 | P76: =IF(COUNTIF(B:B,B76)>1,"Yes","No") -> No | Q76: =IF(F76="","No Code","Used Code") -> Used Code
A77: 5288 | B77: C135 | C77: P04 | D77: 45853 | E77: Bank Transfer | F77: VIP20 | G77: =INDEX(Customers!B:B,MATCH(B77,Customers!A:A,0)) -> Nancy Martin | H77: =INDEX(Customers!E:E,MATCH(B77,Customers!A:A,0)) -> Female | I77: =INDEX(Customers!C:C,MATCH(B77,Customers!A:A,0)) -> 52 | J77: =INDEX(Customers!D:D,MATCH(B77,Customers!A:A,0)) -> Abuja | K77: =INDEX(Products!B:B,MATCH(C77,Products!A:A,0)) -> Clothing | L77: =INDEX(Products!C:C,MATCH(C77,Products!A:A,0)) -> Maxi Gown | M77: =INDEX(Products!D:D,MATCH(C77,Products!A:A,0)) -> 120 | N77: =CHOOSE(MONTH(D77),"Winter","Winter","Spring","Spring","Spring","Summer","Summer","Summer","Fall","Fall","Fall","Winter") -> Summer | O77: =IF(I77<20,"<20",IF(I77<40,"20-40",IF(I77<60,"40-60","60+"))) -> 40-60 | P77: =IF(COUNTIF(B:B,B77)>1,"Yes","No") -> Yes | Q77: =IF(F77="","No Code","Used Code") -> Used Code
A78: 5168 | B78: C082 | C78: P13 | D78: 46044 | E78: Bank Transfer | G78: =INDEX(Customers!B:B,MATCH(B78,Customers!A:A,0)) -> Emeka Martin | H78: =INDEX(Customers!E:E,MATCH(B78,Customers!A:A,0)) -> Male | I78: =INDEX(Customers!C:C,MATCH(B78,Customers!A:A,0)) -> 30 | J78: =INDEX(Customers!D:D,MATCH(B78,Customers!A:A,0)) -> Calabar | K78: =INDEX(Products!B:B,MATCH(C78,Products!A:A,0)) -> Accessories | L78: =INDEX(Products!C:C,MATCH(C78,Products!A:A,0)) -> Sunglasses | M78: =INDEX(Products!D:D,MATCH(C78,Products!A:A,0)) -> 38 | N78: =CHOOSE(MONTH(D78),"Winter","Winter","Spring","Spring","Spring","Summer","Summer","Summer","Fall","Fall","Fall","Winter") -> Winter | O78: =IF(I78<20,"<20",IF(I78<40,"20-40",IF(I78<60,"40-60","60+"))) -> 20-40 | P78: =IF(COUNTIF(B:B,B78)>1,"Yes","No") -> Yes | Q78: =IF(F78="","No Code","Used Code") -> No Code
A79: 5222 | B79: C111 | C79: P16 | D79: 45947 | E79: Card | G79: =INDEX(Customers!B:B,MATCH(B79,Customers!A:A,0)) -> Emeka Harris | H79: =INDEX(Customers!E:E,MATCH(B79,Customers!A:A,0)) -> Male | I79: =INDEX(Customers!C:C,MATCH(B79,Customers!A:A,0)) -> 39 | J79: =INDEX(Customers!D:D,MATCH(B79,Customers!A:A,0)) -> Owerri | K79: =INDEX(Products!B:B,MATCH(C79,Products!A:A,0)) -> Accessories | L79: =INDEX(Products!C:C,MATCH(C79,Products!A:A,0)) -> Bangle Set | M79: =INDEX(Products!D:D,MATCH(C79,Products!A:A,0)) -> 22 | N79: =CHOOSE(MONTH(D79),"Winter","Winter","Spring","Spring","Spring","Summer","Summer","Summer","Fall","Fall","Fall","Winter") -> Fall | O79: =IF(I79<20,"<20",IF(I79<40,"20-40",IF(I79<60,"40-60","60+"))) -> 20-40 | P79: =IF(COUNTIF(B:B,B79)>1,"Yes","No") -> No | Q79: =IF(F79="","No Code","Used Code") -> No Code
A80: 5023 | B80: C010 | C80: P03 | D80: 45959 | E80: PayPal | G80: =INDEX(Customers!B:B,MATCH(B80,Customers!A:A,0)) -> Grace Anderson | H80: =INDEX(Customers!E:E,MATCH(B80,Customers!A:A,0)) -> Female | I80: =INDEX(Customers!C:C,MATCH(B80,Customers!A:A,0)) -> 54 | J80: =INDEX(Customers!D:D,MATCH(B80,Customers!A:A,0)) -> Abeokuta | K80: =INDEX(Products!B:B,MATCH(C80,Products!A:A,0)) -> Clothing | L80: =INDEX(Products!C:C,MATCH(C80,Products!A:A,0)) -> Silk Blouse | M80: =INDEX(Products!D:D,MATCH(C80,Products!A:A,0)) -> 54 | N80: =CHOOSE(MONTH(D80),"Winter","Winter","Spring","Spring","Spring","Summer","Summer","Summer","Fall","Fall","Fall","Winter") -> Fall | O80: =IF(I80<20,"<20",IF(I80<40,"20-40",IF(I80<60,"40-60","60+"))) -> 40-60 | P80: =IF(COUNTIF(B:B,B80)>1,"Yes","No") -> Yes | Q80: =IF(F80="","No Code","Used Code") -> No Code
A81: 5155 | B81: C076 | C81: P06 | D81: 45950 | E81: Cash on Delivery | G81: =INDEX(Customers!B:B,MATCH(B81,Customers!A:A,0)) -> Michael Martin | H81: =INDEX(Customers!E:E,MATCH(B81,Customers!A:A,0)) -> Male | I81: =INDEX(Customers!C:C,MATCH(B81,Customers!A:A,0)) -> 53 | J81: =INDEX(Customers!D:D,MATCH(B81,Customers!A:A,0)) -> Unknown | K81: =INDEX(Products!B:B,MATCH(C81,Products!A:A,0)) -> Clothing | L81: =INDEX(Products!C:C,MATCH(C81,Products!A:A,0)) -> Kaftan | M81: =INDEX(Products!D:D,MATCH(C81,Products!A:A,0)) -> 89 | N81: =CHOOSE(MONTH(D81),"Winter","Winter","Spring","Spring","Spring","Summer","Summer","Summer","Fall","Fall","Fall","Winter") -> Fall | O81: =IF(I81<20,"<20",IF(I81<40,"20-40",IF(I81<60,"40-60","60+"))) -> 40-60 | P81: =IF(COUNTIF(B:B,B81)>1,"Yes","No") -> Yes | Q81: =IF(F81="","No Code","Used Code") -> No Code
A82: 5119 | B82: C057 | C82: P10 | D82: 45895 | E82: Card | F82: FLASH5 | G82: =INDEX(Customers!B:B,MATCH(B82,Customers!A:A,0)) -> Chioma Brown | H82: =INDEX(Customers!E:E,MATCH(B82,Customers!A:A,0)) -> Female | I82: =INDEX(Customers!C:C,MATCH(B82,Customers!A:A,0)) -> 48 | J82: =INDEX(Customers!D:D,MATCH(B82,Customers!A:A,0)) -> Uyo | K82: =INDEX(Products!B:B,MATCH(C82,Products!A:A,0)) -> Clothing | L82: =INDEX(Products!C:C,MATCH(C82,Products!A:A,0)) -> Knit Sweater | M82: =INDEX(Products!D:D,MATCH(C82,Products!A:A,0)) -> 58 | N82: =CHOOSE(MONTH(D82),"Winter","Winter","Spring","Spring","Spring","Summer","Summer","Summer","Fall","Fall","Fall","Winter") -> Summer | O82: =IF(I82<20,"<20",IF(I82<40,"20-40",IF(I82<60,"40-60","60+"))) -> 40-60 | P82: =IF(COUNTIF(B:B,B82)>1,"Yes","No") -> Yes | Q82: =IF(F82="","No Code","Used Code") -> Used Code
A83: 5042 | B83: C019 | C83: P05 | D83: 45971 | E83: Card | G83: =INDEX(Customers!B:B,MATCH(B83,Customers!A:A,0)) -> Karen Anderson | H83: =INDEX(Customers!E:E,MATCH(B83,Customers!A:A,0)) -> Female | I83: =INDEX(Customers!C:C,MATCH(B83,Customers!A:A,0)) -> 38 | J83: =INDEX(Customers!D:D,MATCH(B83,Customers!A:A,0)) -> Enugu | K83: =INDEX(Products!B:B,MATCH(C83,Products!A:A,0)) -> Clothing | L83: =INDEX(Products!C:C,MATCH(C83,Products!A:A,0)) -> Linen Trousers | M83: =INDEX(Products!D:D,MATCH(C83,Products!A:A,0)) -> 47 | N83: =CHOOSE(MONTH(D83),"Winter","Winter","Spring","Spring","Spring","Summer","Summer","Summer","Fall","Fall","Fall","Winter") -> Fall | O83: =IF(I83<20,"<20",IF(I83<40,"20-40",IF(I83<60,"40-60","60+"))) -> 20-40 | P83: =IF(COUNTIF(B:B,B83)>1,"Yes","No") -> No | Q83: =IF(F83="","No Code","Used Code") -> No Code
A84: 5177 | B84: C088 | C84: P04 | D84: 45870 | E84: PayPal | G84: =INDEX(Customers!B:B,MATCH(B84,Customers!A:A,0)) -> Grace Wilson | H84: =INDEX(Customers!E:E,MATCH(B84,Customers!A:A,0)) -> Female | I84: =INDEX(Customers!C:C,MATCH(B84,Customers!A:A,0)) -> 49 | J84: =INDEX(Customers!D:D,MATCH(B84,Customers!A:A,0)) -> Port Harcourt | K84: =INDEX(Products!B:B,MATCH(C84,Products!A:A,0)) -> Clothing | L84: =INDEX(Products!C:C,MATCH(C84,Products!A:A,0)) -> Maxi Gown | M84: =INDEX(Products!D:D,MATCH(C84,Products!A:A,0)) -> 120 | N84: =CHOOSE(MONTH(D84),"Winter","Winter","Spring","Spring","Spring","Summer","Summer","Summer","Fall","Fall","Fall","Winter") -> Summer | O84: =IF(I84<20,"<20",IF(I84<40,"20-40",IF(I84<60,"40-60","60+"))) -> 40-60 | P84: =IF(COUNTIF(B:B,B84)>1,"Yes","No") -> No | Q84: =IF(F84="","No Code","Used Code") -> No Code
A85: 5035 | B85: C014 | C85: P13 | D85: 46073 | E85: Bank Transfer | F85: FLASH5 | G85: =INDEX(Customers!B:B,MATCH(B85,Customers!A:A,0)) -> Mark Davis | H85: =INDEX(Customers!E:E,MATCH(B85,Customers!A:A,0)) -> Male | I85: =INDEX(Customers!C:C,MATCH(B85,Customers!A:A,0)) -> 33 | J85: =INDEX(Customers!D:D,MATCH(B85,Customers!A:A,0)) -> Jos | K85: =INDEX(Products!B:B,MATCH(C85,Products!A:A,0)) -> Accessories | L85: =INDEX(Products!C:C,MATCH(C85,Products!A:A,0)) -> Sunglasses | M85: =INDEX(Products!D:D,MATCH(C85,Products!A:A,0)) -> 38 | N85: =CHOOSE(MONTH(D85),"Winter","Winter","Spring","Spring","Spring","Summer","Summer","Summer","Fall","Fall","Fall","Winter") -> Winter | O85: =IF(I85<20,"<20",IF(I85<40,"20-40",IF(I85<60,"40-60","60+"))) -> 20-40 | P85: =IF(COUNTIF(B:B,B85)>1,"Yes","No") -> Yes | Q85: =IF(F85="","No Code","Used Code") -> Used Code
A86: 5207 | B86: C103 | C86: P15 | D86: 45958 | E86: Bank Transfer | G86: =INDEX(Customers!B:B,MATCH(B86,Customers!A:A,0)) -> Chukwudi Adeyemi | H86: =INDEX(Customers!E:E,MATCH(B86,Customers!A:A,0)) -> Male | I86: =INDEX(Customers!C:C,MATCH(B86,Customers!A:A,0)) -> 20 | J86: =INDEX(Customers!D:D,MATCH(B86,Customers!A:A,0)) -> Owerri | K86: =INDEX(Products!B:B,MATCH(C86,Products!A:A,0)) -> Accessories | L86: =INDEX(Products!C:C,MATCH(C86,Products!A:A,0)) -> Tote Bag | M86: =INDEX(Products!D:D,MATCH(C86,Products!A:A,0)) -> 62 | N86: =CHOOSE(MONTH(D86),"Winter","Winter","Spring","Spring","Spring","Summer","Summer","Summer","Fall","Fall","Fall","Winter") -> Fall | O86: =IF(I86<20,"<20",IF(I86<40,"20-40",IF(I86<60,"40-60","60+"))) -> 20-40 | P86: =IF(COUNTIF(B:B,B86)>1,"Yes","No") -> No | Q86: =IF(F86="","No Code","Used Code") -> No Code
A87: 5040 | B87: C017 | C87: P03 | D87: 46151 | E87: PayPal | G87: =INDEX(Customers!B:B,MATCH(B87,Customers!A:A,0)) -> Grace Taylor | H87: =INDEX(Customers!E:E,MATCH(B87,Customers!A:A,0)) -> Female | I87: =INDEX(Customers!C:C,MATCH(B87,Customers!A:A,0)) -> 44 | J87: =INDEX(Customers!D:D,MATCH(B87,Customers!A:A,0)) -> Port Harcourt | K87: =INDEX(Products!B:B,MATCH(C87,Products!A:A,0)) -> Clothing | L87: =INDEX(Products!C:C,MATCH(C87,Products!A:A,0)) -> Silk Blouse | M87: =INDEX(Products!D:D,MATCH(C87,Products!A:A,0)) -> 54 | N87: =CHOOSE(MONTH(D87),"Winter","Winter","Spring","Spring","Spring","Summer","Summer","Summer","Fall","Fall","Fall","Winter") -> Spring | O87: =IF(I87<20,"<20",IF(I87<40,"20-40",IF(I87<60,"40-60","60+"))) -> 40-60 | P87: =IF(COUNTIF(B:B,B87)>1,"Yes","No") -> Yes | Q87: =IF(F87="","No Code","Used Code") -> No Code
A88: 5162 | B88: C079 | C88: P12 | D88: 46025 | E88: Cash on Delivery | G88: =INDEX(Customers!B:B,MATCH(B88,Customers!A:A,0)) -> Zainab Miller | H88: =INDEX(Customers!E:E,MATCH(B88,Customers!A:A,0)) -> Female | I88: =INDEX(Customers!C:C,MATCH(B88,Customers!A:A,0)) -> 57 | J88: =INDEX(Customers!D:D,MATCH(B88,Customers!A:A,0)) -> Owerri | K88: =INDEX(Products!B:B,MATCH(C88,Products!A:A,0)) -> Accessories | L88: =INDEX(Products!C:C,MATCH(C88,Products!A:A,0)) -> Leather Handbag | M88: =INDEX(Products!D:D,MATCH(C88,Products!A:A,0)) -> 145 | N88: =CHOOSE(MONTH(D88),"Winter","Winter","Spring","Spring","Spring","Summer","Summer","Summer","Fall","Fall","Fall","Winter") -> Winter | O88: =IF(I88<20,"<20",IF(I88<40,"20-40",IF(I88<60,"40-60","60+"))) -> 40-60 | P88: =IF(COUNTIF(B:B,B88)>1,"Yes","No") -> No | Q88: =IF(F88="","No Code","Used Code") -> No Code
A89: 5218 | B89: C109 | C89: P11 | D89: 45988 | E89: PayPal | F89: VIP20 | G89: =INDEX(Customers!B:B,MATCH(B89,Customers!A:A,0)) -> Nancy Uche | H89: =INDEX(Customers!E:E,MATCH(B89,Customers!A:A,0)) -> Female | I89: =INDEX(Customers!C:C,MATCH(B89,Customers!A:A,0)) -> 33 | J89: =INDEX(Customers!D:D,MATCH(B89,Customers!A:A,0)) -> Ilorin | K89: =INDEX(Products!B:B,MATCH(C89,Products!A:A,0)) -> Accessories | L89: =INDEX(Products!C:C,MATCH(C89,Products!A:A,0)) -> Beaded Necklace | M89: =INDEX(Products!D:D,MATCH(C89,Products!A:A,0)) -> 25 | N89: =CHOOSE(MONTH(D89),"Winter","Winter","Spring","Spring","Spring","Summer","Summer","Summer","Fall","Fall","Fall","Winter") -> Fall | O89: =IF(I89<20,"<20",IF(I89<40,"20-40",IF(I89<60,"40-60","60+"))) -> 20-40 | P89: =IF(COUNTIF(B:B,B89)>1,"Yes","No") -> No | Q89: =IF(F89="","No Code","Used Code") -> Used Code
A90: 5191 | B90: C095 | C90: P17 | D90: 45885 | E90: Card | F90: SEASON15 | G90: =INDEX(Customers!B:B,MATCH(B90,Customers!A:A,0)) -> Grace Johnson | H90: =INDEX(Customers!E:E,MATCH(B90,Customers!A:A,0)) -> Female | I90: =INDEX(Customers!C:C,MATCH(B90,Customers!A:A,0)) -> 34 | J90: =INDEX(Customers!D:D,MATCH(B90,Customers!A:A,0)) -> Kano | K90: =INDEX(Products!B:B,MATCH(C90,Products!A:A,0)) -> Accessories | L90: =INDEX(Products!C:C,MATCH(C90,Products!A:A,0)) -> Ankle Boots | M90: =INDEX(Products!D:D,MATCH(C90,Products!A:A,0)) -> 110 | N90: =CHOOSE(MONTH(D90),"Winter","Winter","Spring","Spring","Spring","Summer","Summer","Summer","Fall","Fall","Fall","Winter") -> Summer | O90: =IF(I90<20,"<20",IF(I90<40,"20-40",IF(I90<60,"40-60","60+"))) -> 20-40 | P90: =IF(COUNTIF(B:B,B90)>1,"Yes","No") -> Yes | Q90: =IF(F90="","No Code","Used Code") -> Used Code
A91: 5149 | B91: C073 | C91: P14 | D91: 46133 | E91: Card | G91: =INDEX(Customers!B:B,MATCH(B91,Customers!A:A,0)) -> Zainab White | H91: =INDEX(Customers!E:E,MATCH(B91,Customers!A:A,0)) -> Female | I91: =INDEX(Customers!C:C,MATCH(B91,Customers!A:A,0)) -> 29 | J91: =INDEX(Customers!D:D,MATCH(B91,Customers!A:A,0)) -> Uyo | K91: =INDEX(Products!B:B,MATCH(C91,Products!A:A,0)) -> Accessories | L91: =INDEX(Products!C:C,MATCH(C91,Products!A:A,0)) -> Hair Scarf | M91: =INDEX(Products!D:D,MATCH(C91,Products!A:A,0)) -> 15 | N91: =CHOOSE(MONTH(D91),"Winter","Winter","Spring","Spring","Spring","Summer","Summer","Summer","Fall","Fall","Fall","Winter") -> Spring | O91: =IF(I91<20,"<20",IF(I91<40,"20-40",IF(I91<60,"40-60","60+"))) -> 20-40 | P91: =IF(COUNTIF(B:B,B91)>1,"Yes","No") -> Yes | Q91: =IF(F91="","No Code","Used Code") -> No Code
A92: 5080 | B92: C036 | C92: P13 | D92: 46036 | E92: Cash on Delivery | G92: =INDEX(Customers!B:B,MATCH(B92,Customers!A:A,0)) -> Kevin Wilson | H92: =INDEX(Customers!E:E,MATCH(B92,Customers!A:A,0)) -> Male | I92: =INDEX(Customers!C:C,MATCH(B92,Customers!A:A,0)) -> 24 | J92: =INDEX(Customers!D:D,MATCH(B92,Customers!A:A,0)) -> Kaduna | K92: =INDEX(Products!B:B,MATCH(C92,Products!A:A,0)) -> Accessories | L92: =INDEX(Products!C:C,MATCH(C92,Products!A:A,0)) -> Sunglasses | M92: =INDEX(Products!D:D,MATCH(C92,Products!A:A,0)) -> 38 | N92: =CHOOSE(MONTH(D92),"Winter","Winter","Spring","Spring","Spring","Summer","Summer","Summer","Fall","Fall","Fall","Winter") -> Winter | O92: =IF(I92<20,"<20",IF(I92<40,"20-40",IF(I92<60,"40-60","60+"))) -> 20-40 | P92: =IF(COUNTIF(B:B,B92)>1,"Yes","No") -> Yes | Q92: =IF(F92="","No Code","Used Code") -> No Code
A93: 5142 | B93: C069 | C93: P03 | D93: 45971 | E93: Bank Transfer | G93: =INDEX(Customers!B:B,MATCH(B93,Customers!A:A,0)) -> Linda Miller | H93: =INDEX(Customers!E:E,MATCH(B93,Customers!A:A,0)) -> Female | I93: =INDEX(Customers!C:C,MATCH(B93,Customers!A:A,0)) -> 34 | J93: =INDEX(Customers!D:D,MATCH(B93,Customers!A:A,0)) -> Owerri | K93: =INDEX(Products!B:B,MATCH(C93,Products!A:A,0)) -> Clothing | L93: =INDEX(Products!C:C,MATCH(C93,Products!A:A,0)) -> Silk Blouse | M93: =INDEX(Products!D:D,MATCH(C93,Products!A:A,0)) -> 54 | N93: =CHOOSE(MONTH(D93),"Winter","Winter","Spring","Spring","Spring","Summer","Summer","Summer","Fall","Fall","Fall","Winter") -> Fall | O93: =IF(I93<20,"<20",IF(I93<40,"20-40",IF(I93<60,"40-60","60+"))) -> 20-40 | P93: =IF(COUNTIF(B:B,B93)>1,"Yes","No") -> Yes | Q93: =IF(F93="","No Code","Used Code") -> No Code
A94: 5105 | B94: C052 | C94: P10 | D94: 45873 | E94: PayPal | F94: FLASH5 | G94: =INDEX(Customers!B:B,MATCH(B94,Customers!A:A,0)) -> Halima Balogun | H94: =INDEX(Customers!E:E,MATCH(B94,Customers!A:A,0)) -> Female | I94: =INDEX(Customers!C:C,MATCH(B94,Customers!A:A,0)) -> 32 | J94: =INDEX(Customers!D:D,MATCH(B94,Customers!A:A,0)) -> Ibadan | K94: =INDEX(Products!B:B,MATCH(C94,Products!A:A,0)) -> Clothing | L94: =INDEX(Products!C:C,MATCH(C94,Products!A:A,0)) -> Knit Sweater | M94: =INDEX(Products!D:D,MATCH(C94,Products!A:A,0)) -> 58 | N94: =CHOOSE(MONTH(D94),"Winter","Winter","Spring","Spring","Spring","Summer","Summer","Summer","Fall","Fall","Fall","Winter") -> Summer | O94: =IF(I94<20,"<20",IF(I94<40,"20-40",IF(I94<60,"40-60","60+"))) -> 20-40 | P94: =IF(COUNTIF(B:B,B94)>1,"Yes","No") -> No | Q94: =IF(F94="","No Code","Used Code") -> Used Code
A95: 5063 | B95: C030 | C95: P20 | D95: 46146 | E95: Debit Card | G95: =INDEX(Customers!B:B,MATCH(B95,Customers!A:A,0)) -> John Adeyemi | H95: =INDEX(Customers!E:E,MATCH(B95,Customers!A:A,0)) -> Male | I95: =INDEX(Customers!C:C,MATCH(B95,Customers!A:A,0)) -> 23 | J95: =INDEX(Customers!D:D,MATCH(B95,Customers!A:A,0)) -> Port Harcourt | K95: =INDEX(Products!B:B,MATCH(C95,Products!A:A,0)) -> Accessories | L95: =INDEX(Products!C:C,MATCH(C95,Products!A:A,0)) -> Waist Belt | M95: =INDEX(Products!D:D,MATCH(C95,Products!A:A,0)) -> 33 | N95: =CHOOSE(MONTH(D95),"Winter","Winter","Spring","Spring","Spring","Summer","Summer","Summer","Fall","Fall","Fall","Winter") -> Spring | O95: =IF(I95<20,"<20",IF(I95<40,"20-40",IF(I95<60,"40-60","60+"))) -> 20-40 | P95: =IF(COUNTIF(B:B,B95)>1,"Yes","No") -> Yes | Q95: =IF(F95="","No Code","Used Code") -> No Code
A96: 5148 | B96: C073 | C96: P09 | D96: 45991 | E96: Bank Transfer | G96: =INDEX(Customers!B:B,MATCH(B96,Customers!A:A,0)) -> Zainab White | H96: =INDEX(Customers!E:E,MATCH(B96,Customers!A:A,0)) -> Female | I96: =INDEX(Customers!C:C,MATCH(B96,Customers!A:A,0)) -> 29 | J96: =INDEX(Customers!D:D,MATCH(B96,Customers!A:A,0)) -> Uyo | K96: =INDEX(Products!B:B,MATCH(C96,Products!A:A,0)) -> Clothing | L96: =INDEX(Products!C:C,MATCH(C96,Products!A:A,0)) -> Wrap Skirt | M96: =INDEX(Products!D:D,MATCH(C96,Products!A:A,0)) -> 42 | N96: =CHOOSE(MONTH(D96),"Winter","Winter","Spring","Spring","Spring","Summer","Summer","Summer","Fall","Fall","Fall","Winter") -> Fall | O96: =IF(I96<20,"<20",IF(I96<40,"20-40",IF(I96<60,"40-60","60+"))) -> 20-40 | P96: =IF(COUNTIF(B:B,B96)>1,"Yes","No") -> Yes | Q96: =IF(F96="","No Code","Used Code") -> No Code
A97: 5048 | B97: C021 | C97: P01 | D97: 45947 | E97: Cash on Delivery | G97: =INDEX(Customers!B:B,MATCH(B97,Customers!A:A,0)) -> James Harris | H97: =INDEX(Customers!E:E,MATCH(B97,Customers!A:A,0)) -> Male | I97: =INDEX(Customers!C:C,MATCH(B97,Customers!A:A,0)) -> 23 | J97: =INDEX(Customers!D:D,MATCH(B97,Customers!A:A,0)) -> Kano | K97: =INDEX(Products!B:B,MATCH(C97,Products!A:A,0)) -> Clothing | L97: =INDEX(Products!C:C,MATCH(C97,Products!A:A,0)) -> Ankara Dress | M97: =INDEX(Products!D:D,MATCH(C97,Products!A:A,0)) -> 68 | N97: =CHOOSE(MONTH(D97),"Winter","Winter","Spring","Spring","Spring","Summer","Summer","Summer","Fall","Fall","Fall","Winter") -> Fall | O97: =IF(I97<20,"<20",IF(I97<40,"20-40",IF(I97<60,"40-60","60+"))) -> 20-40 | P97: =IF(COUNTIF(B:B,B97)>1,"Yes","No") -> Yes | Q97: =IF(F97="","No Code","Used Code") -> No Code
A98: 5101 | B98: C050 | C98: P17 | D98: 45913 | E98: Bank Transfer | G98: =INDEX(Customers!B:B,MATCH(B98,Customers!A:A,0)) -> Nkechi White | H98: =INDEX(Customers!E:E,MATCH(B98,Customers!A:A,0)) -> Female | I98: =INDEX(Customers!C:C,MATCH(B98,Customers!A:A,0)) -> 32 | J98: =INDEX(Customers!D:D,MATCH(B98,Customers!A:A,0)) -> Owerri | K98: =INDEX(Products!B:B,MATCH(C98,Products!A:A,0)) -> Accessories | L98: =INDEX(Products!C:C,MATCH(C98,Products!A:A,0)) -> Ankle Boots | M98: =INDEX(Products!D:D,MATCH(C98,Products!A:A,0)) -> 110 | N98: =CHOOSE(MONTH(D98),"Winter","Winter","Spring","Spring","Spring","Summer","Summer","Summer","Fall","Fall","Fall","Winter") -> Fall | O98: =IF(I98<20,"<20",IF(I98<40,"20-40",IF(I98<60,"40-60","60+"))) -> 20-40 | P98: =IF(COUNTIF(B:B,B98)>1,"Yes","No") -> Yes | Q98: =IF(F98="","No Code","Used Code") -> No Code
A99: 5269 | B99: C130 | C99: P15 | D99: 45910 | E99: Bank Transfer | F99: VIP20 | G99: =INDEX(Customers!B:B,MATCH(B99,Customers!A:A,0)) -> Linda Chukwu | H99: =INDEX(Customers!E:E,MATCH(B99,Customers!A:A,0)) -> Female | I99: =INDEX(Customers!C:C,MATCH(B99,Customers!A:A,0)) -> 59 | J99: =INDEX(Customers!D:D,MATCH(B99,Customers!A:A,0)) -> Ibadan | K99: =INDEX(Products!B:B,MATCH(C99,Products!A:A,0)) -> Accessories | L99: =INDEX(Products!C:C,MATCH(C99,Products!A:A,0)) -> Tote Bag | M99: =INDEX(Products!D:D,MATCH(C99,Products!A:A,0)) -> 62 | N99: =CHOOSE(MONTH(D99),"Winter","Winter","Spring","Spring","Spring","Summer","Summer","Summer","Fall","Fall","Fall","Winter") -> Fall | O99: =IF(I99<20,"<20",IF(I99<40,"20-40",IF(I99<60,"40-60","60+"))) -> 40-60 | P99: =IF(COUNTIF(B:B,B99)>1,"Yes","No") -> Yes | Q99: =IF(F99="","No Code","Used Code") -> Used Code
A100: 5212 | B100: C106 | C100: P05 | D100: 45830 | E100: Bank Transfer | F100: SEASON15 | G100: =INDEX(Customers!B:B,MATCH(B100,Customers!A:A,0)) -> Rita Moore | H100: =INDEX(Customers!E:E,MATCH(B100,Customers!A:A,0)) -> Female | I100: =INDEX(Customers!C:C,MATCH(B100,Customers!A:A,0)) -> 50 | J100: =INDEX(Customers!D:D,MATCH(B100,Customers!A:A,0)) -> Abeokuta | K100: =INDEX(Products!B:B,MATCH(C100,Products!A:A,0)) -> Clothing | L100: =INDEX(Products!C:C,MATCH(C100,Products!A:A,0)) -> Linen Trousers | M100: =INDEX(Products!D:D,MATCH(C100,Products!A:A,0)) -> 47 | N100: =CHOOSE(MONTH(D100),"Winter","Winter","Spring","Spring","Spring","Summer","Summer","Summer","Fall","Fall","Fall","Winter") -> Summer | O100: =IF(I100<20,"<20",IF(I100<40,"20-40",IF(I100<60,"40-60","60+"))) -> 40-60 | P100: =IF(COUNTIF(B:B,B100)>1,"Yes","No") -> Yes | Q100: =IF(F100="","No Code","Used Code") -> Used Code
...
